{".class":"MypyFile","_fullname":"dns.message","future_import_flags":[],"is_partial_stub_package":false,"is_stub":false,"names":{".class":"SymbolTable","<subclass of \"Key\" and \"bytes\">":{".class":"SymbolTableNode","kind":"Gdef","node":{".class":"TypeInfo","_promote":[],"abstract_attributes":[],"alt_promote":null,"bases":["dns.tsig.Key","builtins.bytes"],"dataclass_transform_spec":null,"declared_metaclass":null,"defn":{".class":"ClassDef","fullname":"dns.message.<subclass of \"Key\" and \"bytes\">","name":"<subclass of \"Key\" and \"bytes\">","type_vars":[]},"deletable_attributes":[],"flags":["is_intersection"],"fullname":"dns.message.<subclass of \"Key\" and \"bytes\">","has_param_spec_type":false,"metaclass_type":null,"metadata":{},"module_name":"dns.message","mro":["dns.message.<subclass of \"Key\" and \"bytes\">","dns.tsig.Key","builtins.bytes","typing.Sequence","typing.Collection","typing.Reversible","typing.Iterable","typing.Container","builtins.object"],"names":{".class":"SymbolTable"},"self_type":null,"slots":null,"tuple_type":null,"type_vars":[],"typeddict_type":null}},"ADDITIONAL":{".class":"SymbolTableNode","kind":"Gdef","node":{".class":"Var","flags":["is_inferred","has_explicit_value"],"fullname":"dns.message.ADDITIONAL","name":"ADDITIONAL","type":"dns.message.MessageSection"}},"ANSWER":{".class":"SymbolTableNode","kind":"Gdef","node":{".class":"Var","flags":["is_inferred","has_explicit_value"],"fullname":"dns.message.ANSWER","name":"ANSWER","type":"dns.message.MessageSection"}},"AUTHORITY":{".class":"SymbolTableNode","kind":"Gdef","node":{".class":"Var","flags":["is_inferred","has_explicit_value"],"fullname":"dns.message.AUTHORITY","name":"AUTHORITY","type":"dns.message.MessageSection"}},"AnswerForNXDOMAIN":{".class":"SymbolTableNode","kind":"Gdef","node":{".class":"TypeInfo","_promote":[],"abstract_attributes":[],"alt_promote":null,"bases":["dns.exception.DNSException"],"dataclass_transform_spec":null,"declared_metaclass":null,"defn":{".class":"ClassDef","fullname":"dns.message.AnswerForNXDOMAIN","name":"AnswerForNXDOMAIN","type_vars":[]},"deletable_attributes":[],"flags":[],"fullname":"dns.message.AnswerForNXDOMAIN","has_param_spec_type":false,"metaclass_type":null,"metadata":{},"module_name":"dns.message","mro":["dns.message.AnswerForNXDOMAIN","dns.exception.DNSException","builtins.Exception","builtins.BaseException","builtins.object"],"names":{".class":"SymbolTable"},"self_type":{".class":"TypeVarType","default":{".class":"AnyType","missing_import_name":null,"source_any":null,"type_of_any":4},"fullname":"dns.message.AnswerForNXDOMAIN.Self","id":0,"name":"Self","namespace":"","upper_bound":"dns.message.AnswerForNXDOMAIN","values":[],"variance":0},"slots":null,"tuple_type":null,"type_vars":[],"typeddict_type":null}},"Any":{".class":"SymbolTableNode","cross_ref":"typing.Any","kind":"Gdef"},"BadEDNS":{".class":"SymbolTableNode","kind":"Gdef","node":{".class":"TypeInfo","_promote":[],"abstract_attributes":[],"alt_promote":null,"bases":["dns.exception.FormError"],"dataclass_transform_spec":null,"declared_metaclass":null,"defn":{".class":"ClassDef","fullname":"dns.message.BadEDNS","name":"BadEDNS","type_vars":[]},"deletable_attributes":[],"flags":[],"fullname":"dns.message.BadEDNS","has_param_spec_type":false,"metaclass_type":null,"metadata":{},"module_name":"dns.message","mro":["dns.message.BadEDNS","dns.exception.FormError","dns.exception.DNSException","builtins.Exception","builtins.BaseException","builtins.object"],"names":{".class":"SymbolTable"},"self_type":{".class":"TypeVarType","default":{".class":"AnyType","missing_import_name":null,"source_any":null,"type_of_any":4},"fullname":"dns.message.BadEDNS.Self","id":0,"name":"Self","namespace":"","upper_bound":"dns.message.BadEDNS","values":[],"variance":0},"slots":null,"tuple_type":null,"type_vars":[],"typeddict_type":null}},"BadTSIG":{".class":"SymbolTableNode","kind":"Gdef","node":{".class":"TypeInfo","_promote":[],"abstract_attributes":[],"alt_promote":null,"bases":["dns.exception.FormError"],"dataclass_transform_spec":null,"declared_metaclass":null,"defn":{".class":"ClassDef","fullname":"dns.message.BadTSIG","name":"BadTSIG","type_vars":[]},"deletable_attributes":[],"flags":[],"fullname":"dns.message.BadTSIG","has_param_spec_type":false,"metaclass_type":null,"metadata":{},"module_name":"dns.message","mro":["dns.message.BadTSIG","dns.exception.FormError","dns.exception.DNSException","builtins.Exception","builtins.BaseException","builtins.object"],"names":{".class":"SymbolTable"},"self_type":{".class":"TypeVarType","default":{".class":"AnyType","missing_import_name":null,"source_any":null,"type_of_any":4},"fullname":"dns.message.BadTSIG.Self","id":0,"name":"Self","namespace":"","upper_bound":"dns.message.BadTSIG","values":[],"variance":0},"slots":null,"tuple_type":null,"type_vars":[],"typeddict_type":null}},"ChainTooLong":{".class":"SymbolTableNode","kind":"Gdef","node":{".class":"TypeInfo","_promote":[],"abstract_attributes":[],"alt_promote":null,"bases":["dns.exception.DNSException"],"dataclass_transform_spec":null,"declared_metaclass":null,"defn":{".class":"ClassDef","fullname":"dns.message.ChainTooLong","name":"ChainTooLong","type_vars":[]},"deletable_attributes":[],"flags":[],"fullname":"dns.message.ChainTooLong","has_param_spec_type":false,"metaclass_type":null,"metadata":{},"module_name":"dns.message","mro":["dns.message.ChainTooLong","dns.exception.DNSException","builtins.Exception","builtins.BaseException","builtins.object"],"names":{".class":"SymbolTable"},"self_type":{".class":"TypeVarType","default":{".class":"AnyType","missing_import_name":null,"source_any":null,"type_of_any":4},"fullname":"dns.message.ChainTooLong.Self","id":0,"name":"Self","namespace":"","upper_bound":"dns.message.ChainTooLong","values":[],"variance":0},"slots":null,"tuple_type":null,"type_vars":[],"typeddict_type":null}},"ChainingResult":{".class":"SymbolTableNode","kind":"Gdef","node":{".class":"TypeInfo","_promote":[],"abstract_attributes":[],"alt_promote":null,"bases":["builtins.object"],"dataclass_transform_spec":null,"declared_metaclass":null,"defn":{".class":"ClassDef","fullname":"dns.message.ChainingResult","name":"ChainingResult","type_vars":[]},"deletable_attributes":[],"flags":[],"fullname":"dns.message.ChainingResult","has_param_spec_type":false,"metaclass_type":null,"metadata":{},"module_name":"dns.message","mro":["dns.message.ChainingResult","builtins.object"],"names":{".class":"SymbolTable","__init__":{".class":"SymbolTableNode","kind":"Mdef","node":{".class":"FuncDef","abstract_status":0,"arg_kinds":[0,0,0,0,0],"arg_names":["self","canonical_name","answer","minimum_ttl","cnames"],"dataclass_transform_spec":null,"flags":[],"fullname":"dns.message.ChainingResult.__init__","name":"__init__","type":{".class":"CallableType","arg_kinds":[0,0,0,0,0],"arg_names":["self","canonical_name","answer","minimum_ttl","cnames"],"arg_types":["dns.message.ChainingResult","dns.name.Name",{".class":"UnionType","items":["dns.rrset.RRset",{".class":"NoneType"}]},"builtins.int",{".class":"Instance","args":["dns.rrset.RRset"],"type_ref":"builtins.list"}],"bound_args":[],"def_extras":{"first_arg":"self"},"fallback":"builtins.function","from_concatenate":false,"implicit":false,"imprecise_arg_kinds":false,"is_ellipsis_args":false,"name":"__init__ of ChainingResult","ret_type":{".class":"NoneType"},"type_guard":null,"unpack_kwargs":false,"variables":[]}}},"answer":{".class":"SymbolTableNode","implicit":true,"kind":"Mdef","node":{".class":"Var","flags":["is_inferred"],"fullname":"dns.message.ChainingResult.answer","name":"answer","type":{".class":"UnionType","items":["dns.rrset.RRset",{".class":"NoneType"}]}}},"canonical_name":{".class":"SymbolTableNode","implicit":true,"kind":"Mdef","node":{".class":"Var","flags":["is_inferred"],"fullname":"dns.message.ChainingResult.canonical_name","name":"canonical_name","type":"dns.name.Name"}},"cnames":{".class":"SymbolTableNode","implicit":true,"kind":"Mdef","node":{".class":"Var","flags":["is_inferred"],"fullname":"dns.message.ChainingResult.cnames","name":"cnames","type":{".class":"Instance","args":["dns.rrset.RRset"],"type_ref":"builtins.list"}}},"minimum_ttl":{".class":"SymbolTableNode","implicit":true,"kind":"Mdef","node":{".class":"Var","flags":["is_inferred"],"fullname":"dns.message.ChainingResult.minimum_ttl","name":"minimum_ttl","type":"builtins.int"}}},"self_type":{".class":"TypeVarType","default":{".class":"AnyType","missing_import_name":null,"source_any":null,"type_of_any":4},"fullname":"dns.message.ChainingResult.Self","id":0,"name":"Self","namespace":"","upper_bound":"dns.message.ChainingResult","values":[],"variance":0},"slots":null,"tuple_type":null,"type_vars":[],"typeddict_type":null}},"DEFAULT_EDNS_PAYLOAD":{".class":"SymbolTableNode","kind":"Gdef","node":{".class":"Var","flags":["is_ready","is_inferred","has_explicit_value"],"fullname":"dns.message.DEFAULT_EDNS_PAYLOAD","name":"DEFAULT_EDNS_PAYLOAD","type":"builtins.int"}},"Dict":{".class":"SymbolTableNode","cross_ref":"typing.Dict","kind":"Gdef"},"IndexKeyType":{".class":"SymbolTableNode","kind":"Gdef","node":{".class":"TypeAlias","alias_tvars":[],"column":0,"fullname":"dns.message.IndexKeyType","line":128,"no_args":false,"normalized":false,"target":{".class":"TupleType","implicit":false,"items":["builtins.int","dns.name.Name","dns.rdataclass.RdataClass","dns.rdatatype.RdataType",{".class":"UnionType","items":["dns.rdatatype.RdataType",{".class":"NoneType"}]},{".class":"UnionType","items":["dns.rdataclass.RdataClass",{".class":"NoneType"}]}],"partial_fallback":{".class":"Instance","args":[{".class":"AnyType","missing_import_name":null,"source_any":null,"type_of_any":6}],"type_ref":"builtins.tuple"}}}},"IndexType":{".class":"SymbolTableNode","kind":"Gdef","node":{".class":"TypeAlias","alias_tvars":[],"column":0,"fullname":"dns.message.IndexType","line":136,"no_args":false,"normalized":false,"target":{".class":"Instance","args":[{".class":"TypeAliasType","args":[],"type_ref":"dns.message.IndexKeyType"},"dns.rrset.RRset"],"type_ref":"builtins.dict"}}},"List":{".class":"SymbolTableNode","cross_ref":"typing.List","kind":"Gdef"},"MAX_CHAIN":{".class":"SymbolTableNode","kind":"Gdef","node":{".class":"Var","flags":["is_ready","is_inferred","has_explicit_value"],"fullname":"dns.message.MAX_CHAIN","name":"MAX_CHAIN","type":"builtins.int"}},"Message":{".class":"SymbolTableNode","kind":"Gdef","node":{".class":"TypeInfo","_promote":[],"abstract_attributes":[],"alt_promote":null,"bases":["builtins.object"],"dataclass_transform_spec":null,"declared_metaclass":null,"defn":{".class":"ClassDef","fullname":"dns.message.Message","name":"Message","type_vars":[]},"deletable_attributes":[],"flags":[],"fullname":"dns.message.Message","has_param_spec_type":false,"metaclass_type":null,"metadata":{},"module_name":"dns.message","mro":["dns.message.Message","builtins.object"],"names":{".class":"SymbolTable","__eq__":{".class":"SymbolTableNode","kind":"Mdef","node":{".class":"FuncDef","abstract_status":0,"arg_kinds":[0,0],"arg_names":[null,null],"dataclass_transform_spec":null,"flags":[],"fullname":"dns.message.Message.__eq__","name":"__eq__","type":null}},"__init__":{".class":"SymbolTableNode","kind":"Mdef","node":{".class":"FuncDef","abstract_status":0,"arg_kinds":[0,1],"arg_names":["self","id"],"dataclass_transform_spec":null,"flags":[],"fullname":"dns.message.Message.__init__","name":"__init__","type":{".class":"CallableType","arg_kinds":[0,1],"arg_names":["self","id"],"arg_types":["dns.message.Message",{".class":"UnionType","items":["builtins.int",{".class":"NoneType"}]}],"bound_args":[],"def_extras":{"first_arg":"self"},"fallback":"builtins.function","from_concatenate":false,"implicit":false,"imprecise_arg_kinds":false,"is_ellipsis_args":false,"name":"__init__ of Message","ret_type":{".class":"NoneType"},"type_guard":null,"unpack_kwargs":false,"variables":[]}}},"__ne__":{".class":"SymbolTableNode","kind":"Mdef","node":{".class":"FuncDef","abstract_status":0,"arg_kinds":[0,0],"arg_names":[null,null],"dataclass_transform_spec":null,"flags":[],"fullname":"dns.message.Message.__ne__","name":"__ne__","type":null}},"__repr__":{".class":"SymbolTableNode","kind":"Mdef","node":{".class":"FuncDef","abstract_status":0,"arg_kinds":[0],"arg_names":[null],"dataclass_transform_spec":null,"flags":[],"fullname":"dns.message.Message.__repr__","name":"__repr__","type":null}},"__str__":{".class":"SymbolTableNode","kind":"Mdef","node":{".class":"FuncDef","abstract_status":0,"arg_kinds":[0],"arg_names":[null],"dataclass_transform_spec":null,"flags":[],"fullname":"dns.message.Message.__str__","name":"__str__","type":null}},"_compute_opt_reserve":{".class":"SymbolTableNode","kind":"Mdef","node":{".class":"FuncDef","abstract_status":0,"arg_kinds":[0],"arg_names":["self"],"dataclass_transform_spec":null,"flags":[],"fullname":"dns.message.Message._compute_opt_reserve","name":"_compute_opt_reserve","type":{".class":"CallableType","arg_kinds":[0],"arg_names":["self"],"arg_types":["dns.message.Message"],"bound_args":[],"def_extras":{"first_arg":"self"},"fallback":"builtins.function","from_concatenate":false,"implicit":false,"imprecise_arg_kinds":false,"is_ellipsis_args":false,"name":"_compute_opt_reserve of Message","ret_type":"builtins.int","type_guard":null,"unpack_kwargs":false,"variables":[]}}},"_compute_tsig_reserve":{".class":"SymbolTableNode","kind":"Mdef","node":{".class":"FuncDef","abstract_status":0,"arg_kinds":[0],"arg_names":["self"],"dataclass_transform_spec":null,"flags":[],"fullname":"dns.message.Message._compute_tsig_reserve","name":"_compute_tsig_reserve","type":{".class":"CallableType","arg_kinds":[0],"arg_names":["self"],"arg_types":["dns.message.Message"],"bound_args":[],"def_extras":{"first_arg":"self"},"fallback":"builtins.function","from_concatenate":false,"implicit":false,"imprecise_arg_kinds":false,"is_ellipsis_args":false,"name":"_compute_tsig_reserve of Message","ret_type":"builtins.int","type_guard":null,"unpack_kwargs":false,"variables":[]}}},"_get_one_rr_per_rrset":{".class":"SymbolTableNode","kind":"Mdef","node":{".class":"FuncDef","abstract_status":0,"arg_kinds":[0,0],"arg_names":["self","value"],"dataclass_transform_spec":null,"flags":[],"fullname":"dns.message.Message._get_one_rr_per_rrset","name":"_get_one_rr_per_rrset","type":null}},"_make_opt":{".class":"SymbolTableNode","kind":"Mdef","node":{".class":"Decorator","func":{".class":"FuncDef","abstract_status":0,"arg_kinds":[1,1,1],"arg_names":["flags","payload","options"],"dataclass_transform_spec":null,"flags":["is_static","is_decorated"],"fullname":"dns.message.Message._make_opt","name":"_make_opt","type":null},"is_overload":false,"var":{".class":"Var","flags":["is_initialized_in_class","is_staticmethod","is_ready","is_inferred"],"fullname":"dns.message.Message._make_opt","name":"_make_opt","type":{".class":"CallableType","arg_kinds":[1,1,1],"arg_names":["flags","payload","options"],"arg_types":[{".class":"AnyType","missing_import_name":null,"source_any":null,"type_of_any":1},{".class":"AnyType","missing_import_name":null,"source_any":null,"type_of_any":1},{".class":"AnyType","missing_import_name":null,"source_any":null,"type_of_any":1}],"bound_args":[],"def_extras":{"first_arg":null},"fallback":"builtins.function","from_concatenate":false,"implicit":true,"imprecise_arg_kinds":false,"is_ellipsis_args":false,"name":"_make_opt of Message","ret_type":{".class":"AnyType","missing_import_name":null,"source_any":null,"type_of_any":1},"type_guard":null,"unpack_kwargs":false,"variables":[]}}}},"_make_tsig":{".class":"SymbolTableNode","kind":"Mdef","node":{".class":"Decorator","func":{".class":"FuncDef","abstract_status":0,"arg_kinds":[0,0,0,0,0,0,0,0],"arg_names":["keyname","algorithm","time_signed","fudge","mac","original_id","error","other"],"dataclass_transform_spec":null,"flags":["is_static","is_decorated"],"fullname":"dns.message.Message._make_tsig","name":"_make_tsig","type":null},"is_overload":false,"var":{".class":"Var","flags":["is_initialized_in_class","is_staticmethod","is_ready","is_inferred"],"fullname":"dns.message.Message._make_tsig","name":"_make_tsig","type":{".class":"CallableType","arg_kinds":[0,0,0,0,0,0,0,0],"arg_names":["keyname","algorithm","time_signed","fudge","mac","original_id","error","other"],"arg_types":[{".class":"AnyType","missing_import_name":null,"source_any":null,"type_of_any":1},{".class":"AnyType","missing_import_name":null,"source_any":null,"type_of_any":1},{".class":"AnyType","missing_import_name":null,"source_any":null,"type_of_any":1},{".class":"AnyType","missing_import_name":null,"source_any":null,"type_of_any":1},{".class":"AnyType","missing_import_name":null,"source_any":null,"type_of_any":1},{".class":"AnyType","missing_import_name":null,"source_any":null,"type_of_any":1},{".class":"AnyType","missing_import_name":null,"source_any":null,"type_of_any":1},{".class":"AnyType","missing_import_name":null,"source_any":null,"type_of_any":1}],"bound_args":[],"def_extras":{"first_arg":null},"fallback":"builtins.function","from_concatenate":false,"implicit":true,"imprecise_arg_kinds":false,"is_ellipsis_args":false,"name":"_make_tsig of Message","ret_type":{".class":"AnyType","missing_import_name":null,"source_any":null,"type_of_any":1},"type_guard":null,"unpack_kwargs":false,"variables":[]}}}},"_parse_rr_header":{".class":"SymbolTableNode","kind":"Mdef","node":{".class":"FuncDef","abstract_status":0,"arg_kinds":[0,0,0,0,0],"arg_names":["self","section","name","rdclass","rdtype"],"dataclass_transform_spec":null,"flags":[],"fullname":"dns.message.Message._parse_rr_header","name":"_parse_rr_header","type":null}},"_parse_special_rr_header":{".class":"SymbolTableNode","kind":"Mdef","node":{".class":"FuncDef","abstract_status":0,"arg_kinds":[0,0,0,0,0,0,0],"arg_names":["self","section","count","position","name","rdclass","rdtype"],"dataclass_transform_spec":null,"flags":[],"fullname":"dns.message.Message._parse_special_rr_header","name":"_parse_special_rr_header","type":null}},"_section_enum":{".class":"SymbolTableNode","kind":"Mdef","node":{".class":"Var","flags":["is_initialized_in_class","is_inferred","has_explicit_value"],"fullname":"dns.message.Message._section_enum","name":"_section_enum","type":{".class":"CallableType","arg_kinds":[0],"arg_names":["value"],"arg_types":["builtins.int"],"bound_args":["dns.message.MessageSection"],"def_extras":{"first_arg":null},"fallback":"enum.EnumMeta","from_concatenate":false,"implicit":false,"imprecise_arg_kinds":false,"is_ellipsis_args":false,"name":null,"ret_type":"dns.message.MessageSection","type_guard":null,"unpack_kwargs":false,"variables":[]}}},"additional":{".class":"SymbolTableNode","kind":"Mdef","node":{".class":"OverloadedFuncDef","flags":["is_property"],"fullname":"dns.message.Message.additional","impl":null,"items":[{".class":"Decorator","func":{".class":"FuncDef","abstract_status":0,"arg_kinds":[0],"arg_names":["self"],"dataclass_transform_spec":null,"flags":["is_property","is_overload","is_decorated"],"fullname":"dns.message.Message.additional","name":"additional","type":{".class":"CallableType","arg_kinds":[0],"arg_names":["self"],"arg_types":["dns.message.Message"],"bound_args":[],"def_extras":{"first_arg":"self"},"fallback":"builtins.function","from_concatenate":false,"implicit":false,"imprecise_arg_kinds":false,"is_ellipsis_args":false,"name":"additional of Message","ret_type":{".class":"Instance","args":["dns.rrset.RRset"],"type_ref":"builtins.list"},"type_guard":null,"unpack_kwargs":false,"variables":[]}},"is_overload":true,"var":{".class":"Var","flags":["is_initialized_in_class","is_property","is_settable_property","is_ready","is_inferred"],"fullname":"dns.message.Message.additional","name":"additional","type":{".class":"CallableType","arg_kinds":[0],"arg_names":["self"],"arg_types":["dns.message.Message"],"bound_args":[],"def_extras":{"first_arg":"self"},"fallback":"builtins.function","from_concatenate":false,"implicit":false,"imprecise_arg_kinds":false,"is_ellipsis_args":false,"name":"additional of Message","ret_type":{".class":"Instance","args":["dns.rrset.RRset"],"type_ref":"builtins.list"},"type_guard":null,"unpack_kwargs":false,"variables":[]}}},{".class":"Decorator","func":{".class":"FuncDef","abstract_status":0,"arg_kinds":[0,0],"arg_names":["self","v"],"dataclass_transform_spec":null,"flags":["is_decorated"],"fullname":"dns.message.Message.additional","name":"additional","type":null},"is_overload":false,"var":{".class":"Var","flags":["is_inferred"],"fullname":"","name":"additional","type":null}}],"type":{".class":"Overloaded","items":[{".class":"CallableType","arg_kinds":[0],"arg_names":["self"],"arg_types":["dns.message.Message"],"bound_args":[],"def_extras":{"first_arg":"self"},"fallback":"builtins.function","from_concatenate":false,"implicit":false,"imprecise_arg_kinds":false,"is_ellipsis_args":false,"name":"additional of Message","ret_type":{".class":"Instance","args":["dns.rrset.RRset"],"type_ref":"builtins.list"},"type_guard":null,"unpack_kwargs":false,"variables":[]}]}}},"answer":{".class":"SymbolTableNode","kind":"Mdef","node":{".class":"OverloadedFuncDef","flags":["is_property"],"fullname":"dns.message.Message.answer","impl":null,"items":[{".class":"Decorator","func":{".class":"FuncDef","abstract_status":0,"arg_kinds":[0],"arg_names":["self"],"dataclass_transform_spec":null,"flags":["is_property","is_overload","is_decorated"],"fullname":"dns.message.Message.answer","name":"answer","type":{".class":"CallableType","arg_kinds":[0],"arg_names":["self"],"arg_types":["dns.message.Message"],"bound_args":[],"def_extras":{"first_arg":"self"},"fallback":"builtins.function","from_concatenate":false,"implicit":false,"imprecise_arg_kinds":false,"is_ellipsis_args":false,"name":"answer of Message","ret_type":{".class":"Instance","args":["dns.rrset.RRset"],"type_ref":"builtins.list"},"type_guard":null,"unpack_kwargs":false,"variables":[]}},"is_overload":true,"var":{".class":"Var","flags":["is_initialized_in_class","is_property","is_settable_property","is_ready","is_inferred"],"fullname":"dns.message.Message.answer","name":"answer","type":{".class":"CallableType","arg_kinds":[0],"arg_names":["self"],"arg_types":["dns.message.Message"],"bound_args":[],"def_extras":{"first_arg":"self"},"fallback":"builtins.function","from_concatenate":false,"implicit":false,"imprecise_arg_kinds":false,"is_ellipsis_args":false,"name":"answer of Message","ret_type":{".class":"Instance","args":["dns.rrset.RRset"],"type_ref":"builtins.list"},"type_guard":null,"unpack_kwargs":false,"variables":[]}}},{".class":"Decorator","func":{".class":"FuncDef","abstract_status":0,"arg_kinds":[0,0],"arg_names":["self","v"],"dataclass_transform_spec":null,"flags":["is_decorated"],"fullname":"dns.message.Message.answer","name":"answer","type":null},"is_overload":false,"var":{".class":"Var","flags":["is_inferred"],"fullname":"","name":"answer","type":null}}],"type":{".class":"Overloaded","items":[{".class":"CallableType","arg_kinds":[0],"arg_names":["self"],"arg_types":["dns.message.Message"],"bound_args":[],"def_extras":{"first_arg":"self"},"fallback":"builtins.function","from_concatenate":false,"implicit":false,"imprecise_arg_kinds":false,"is_ellipsis_args":false,"name":"answer of Message","ret_type":{".class":"Instance","args":["dns.rrset.RRset"],"type_ref":"builtins.list"},"type_guard":null,"unpack_kwargs":false,"variables":[]}]}}},"authority":{".class":"SymbolTableNode","kind":"Mdef","node":{".class":"OverloadedFuncDef","flags":["is_property"],"fullname":"dns.message.Message.authority","impl":null,"items":[{".class":"Decorator","func":{".class":"FuncDef","abstract_status":0,"arg_kinds":[0],"arg_names":["self"],"dataclass_transform_spec":null,"flags":["is_property","is_overload","is_decorated"],"fullname":"dns.message.Message.authority","name":"authority","type":{".class":"CallableType","arg_kinds":[0],"arg_names":["self"],"arg_types":["dns.message.Message"],"bound_args":[],"def_extras":{"first_arg":"self"},"fallback":"builtins.function","from_concatenate":false,"implicit":false,"imprecise_arg_kinds":false,"is_ellipsis_args":false,"name":"authority of Message","ret_type":{".class":"Instance","args":["dns.rrset.RRset"],"type_ref":"builtins.list"},"type_guard":null,"unpack_kwargs":false,"variables":[]}},"is_overload":true,"var":{".class":"Var","flags":["is_initialized_in_class","is_property","is_settable_property","is_ready","is_inferred"],"fullname":"dns.message.Message.authority","name":"authority","type":{".class":"CallableType","arg_kinds":[0],"arg_names":["self"],"arg_types":["dns.message.Message"],"bound_args":[],"def_extras":{"first_arg":"self"},"fallback":"builtins.function","from_concatenate":false,"implicit":false,"imprecise_arg_kinds":false,"is_ellipsis_args":false,"name":"authority of Message","ret_type":{".class":"Instance","args":["dns.rrset.RRset"],"type_ref":"builtins.list"},"type_guard":null,"unpack_kwargs":false,"variables":[]}}},{".class":"Decorator","func":{".class":"FuncDef","abstract_status":0,"arg_kinds":[0,0],"arg_names":["self","v"],"dataclass_transform_spec":null,"flags":["is_decorated"],"fullname":"dns.message.Message.authority","name":"authority","type":null},"is_overload":false,"var":{".class":"Var","flags":["is_inferred"],"fullname":"","name":"authority","type":null}}],"type":{".class":"Overloaded","items":[{".class":"CallableType","arg_kinds":[0],"arg_names":["self"],"arg_types":["dns.message.Message"],"bound_args":[],"def_extras":{"first_arg":"self"},"fallback":"builtins.function","from_concatenate":false,"implicit":false,"imprecise_arg_kinds":false,"is_ellipsis_args":false,"name":"authority of Message","ret_type":{".class":"Instance","args":["dns.rrset.RRset"],"type_ref":"builtins.list"},"type_guard":null,"unpack_kwargs":false,"variables":[]}]}}},"edns":{".class":"SymbolTableNode","kind":"Mdef","node":{".class":"Decorator","func":{".class":"FuncDef","abstract_status":0,"arg_kinds":[0],"arg_names":["self"],"dataclass_transform_spec":null,"flags":["is_property","is_decorated"],"fullname":"dns.message.Message.edns","name":"edns","type":{".class":"CallableType","arg_kinds":[0],"arg_names":["self"],"arg_types":["dns.message.Message"],"bound_args":[],"def_extras":{"first_arg":"self"},"fallback":"builtins.function","from_concatenate":false,"implicit":false,"imprecise_arg_kinds":false,"is_ellipsis_args":false,"name":"edns of Message","ret_type":"builtins.int","type_guard":null,"unpack_kwargs":false,"variables":[]}},"is_overload":false,"var":{".class":"Var","flags":["is_initialized_in_class","is_property","is_ready","is_inferred"],"fullname":"dns.message.Message.edns","name":"edns","type":{".class":"CallableType","arg_kinds":[0],"arg_names":["self"],"arg_types":["dns.message.Message"],"bound_args":[],"def_extras":{"first_arg":"self"},"fallback":"builtins.function","from_concatenate":false,"implicit":false,"imprecise_arg_kinds":false,"is_ellipsis_args":false,"name":"edns of Message","ret_type":"builtins.int","type_guard":null,"unpack_kwargs":false,"variables":[]}}}},"ednsflags":{".class":"SymbolTableNode","kind":"Mdef","node":{".class":"OverloadedFuncDef","flags":["is_property"],"fullname":"dns.message.Message.ednsflags","impl":null,"items":[{".class":"Decorator","func":{".class":"FuncDef","abstract_status":0,"arg_kinds":[0],"arg_names":["self"],"dataclass_transform_spec":null,"flags":["is_property","is_overload","is_decorated"],"fullname":"dns.message.Message.ednsflags","name":"ednsflags","type":{".class":"CallableType","arg_kinds":[0],"arg_names":["self"],"arg_types":["dns.message.Message"],"bound_args":[],"def_extras":{"first_arg":"self"},"fallback":"builtins.function","from_concatenate":false,"implicit":false,"imprecise_arg_kinds":false,"is_ellipsis_args":false,"name":"ednsflags of Message","ret_type":"builtins.int","type_guard":null,"unpack_kwargs":false,"variables":[]}},"is_overload":true,"var":{".class":"Var","flags":["is_initialized_in_class","is_property","is_settable_property","is_ready","is_inferred"],"fullname":"dns.message.Message.ednsflags","name":"ednsflags","type":{".class":"CallableType","arg_kinds":[0],"arg_names":["self"],"arg_types":["dns.message.Message"],"bound_args":[],"def_extras":{"first_arg":"self"},"fallback":"builtins.function","from_concatenate":false,"implicit":false,"imprecise_arg_kinds":false,"is_ellipsis_args":false,"name":"ednsflags of Message","ret_type":"builtins.int","type_guard":null,"unpack_kwargs":false,"variables":[]}}},{".class":"Decorator","func":{".class":"FuncDef","abstract_status":0,"arg_kinds":[0,0],"arg_names":["self","v"],"dataclass_transform_spec":null,"flags":["is_decorated"],"fullname":"dns.message.Message.ednsflags","name":"ednsflags","type":null},"is_overload":false,"var":{".class":"Var","flags":["is_inferred"],"fullname":"","name":"ednsflags","type":null}}],"type":{".class":"Overloaded","items":[{".class":"CallableType","arg_kinds":[0],"arg_names":["self"],"arg_types":["dns.message.Message"],"bound_args":[],"def_extras":{"first_arg":"self"},"fallback":"builtins.function","from_concatenate":false,"implicit":false,"imprecise_arg_kinds":false,"is_ellipsis_args":false,"name":"ednsflags of Message","ret_type":"builtins.int","type_guard":null,"unpack_kwargs":false,"variables":[]}]}}},"errors":{".class":"SymbolTableNode","implicit":true,"kind":"Mdef","node":{".class":"Var","flags":["explicit_self_type","is_ready","is_inferred"],"fullname":"dns.message.Message.errors","name":"errors","type":{".class":"Instance","args":["dns.message.MessageError"],"type_ref":"builtins.list"}}},"find_rrset":{".class":"SymbolTableNode","kind":"Mdef","node":{".class":"FuncDef","abstract_status":0,"arg_kinds":[0,0,0,0,0,1,1,1,1,1],"arg_names":["self","section","name","rdclass","rdtype","covers","deleting","create","force_unique","idna_codec"],"dataclass_transform_spec":null,"flags":[],"fullname":"dns.message.Message.find_rrset","name":"find_rrset","type":{".class":"CallableType","arg_kinds":[0,0,0,0,0,1,1,1,1,1],"arg_names":["self","section","name","rdclass","rdtype","covers","deleting","create","force_unique","idna_codec"],"arg_types":["dns.message.Message",{".class":"TypeAliasType","args":[],"type_ref":"dns.message.SectionType"},"dns.name.Name","dns.rdataclass.RdataClass","dns.rdatatype.RdataType","dns.rdatatype.RdataType",{".class":"UnionType","items":["dns.rdataclass.RdataClass",{".class":"NoneType"}]},"builtins.bool","builtins.bool",{".class":"UnionType","items":["dns.name.IDNACodec",{".class":"NoneType"}]}],"bound_args":[],"def_extras":{"first_arg":"self"},"fallback":"builtins.function","from_concatenate":false,"implicit":false,"imprecise_arg_kinds":false,"is_ellipsis_args":false,"name":"find_rrset of Message","ret_type":"dns.rrset.RRset","type_guard":null,"unpack_kwargs":false,"variables":[]}}},"flags":{".class":"SymbolTableNode","implicit":true,"kind":"Mdef","node":{".class":"Var","flags":["is_inferred"],"fullname":"dns.message.Message.flags","name":"flags","type":"builtins.int"}},"get_rrset":{".class":"SymbolTableNode","kind":"Mdef","node":{".class":"FuncDef","abstract_status":0,"arg_kinds":[0,0,0,0,0,1,1,1,1,1],"arg_names":["self","section","name","rdclass","rdtype","covers","deleting","create","force_unique","idna_codec"],"dataclass_transform_spec":null,"flags":[],"fullname":"dns.message.Message.get_rrset","name":"get_rrset","type":{".class":"CallableType","arg_kinds":[0,0,0,0,0,1,1,1,1,1],"arg_names":["self","section","name","rdclass","rdtype","covers","deleting","create","force_unique","idna_codec"],"arg_types":["dns.message.Message",{".class":"TypeAliasType","args":[],"type_ref":"dns.message.SectionType"},"dns.name.Name","dns.rdataclass.RdataClass","dns.rdatatype.RdataType","dns.rdatatype.RdataType",{".class":"UnionType","items":["dns.rdataclass.RdataClass",{".class":"NoneType"}]},"builtins.bool","builtins.bool",{".class":"UnionType","items":["dns.name.IDNACodec",{".class":"NoneType"}]}],"bound_args":[],"def_extras":{"first_arg":"self"},"fallback":"builtins.function","from_concatenate":false,"implicit":false,"imprecise_arg_kinds":false,"is_ellipsis_args":false,"name":"get_rrset of Message","ret_type":{".class":"UnionType","items":["dns.rrset.RRset",{".class":"NoneType"}]},"type_guard":null,"unpack_kwargs":false,"variables":[]}}},"had_tsig":{".class":"SymbolTableNode","kind":"Mdef","node":{".class":"Decorator","func":{".class":"FuncDef","abstract_status":0,"arg_kinds":[0],"arg_names":["self"],"dataclass_transform_spec":null,"flags":["is_property","is_decorated"],"fullname":"dns.message.Message.had_tsig","name":"had_tsig","type":{".class":"CallableType","arg_kinds":[0],"arg_names":["self"],"arg_types":["dns.message.Message"],"bound_args":[],"def_extras":{"first_arg":"self"},"fallback":"builtins.function","from_concatenate":false,"implicit":false,"imprecise_arg_kinds":false,"is_ellipsis_args":false,"name":"had_tsig of Message","ret_type":"builtins.bool","type_guard":null,"unpack_kwargs":false,"variables":[]}},"is_overload":false,"var":{".class":"Var","flags":["is_initialized_in_class","is_property","is_ready","is_inferred"],"fullname":"dns.message.Message.had_tsig","name":"had_tsig","type":{".class":"CallableType","arg_kinds":[0],"arg_names":["self"],"arg_types":["dns.message.Message"],"bound_args":[],"def_extras":{"first_arg":"self"},"fallback":"builtins.function","from_concatenate":false,"implicit":false,"imprecise_arg_kinds":false,"is_ellipsis_args":false,"name":"had_tsig of Message","ret_type":"builtins.bool","type_guard":null,"unpack_kwargs":false,"variables":[]}}}},"id":{".class":"SymbolTableNode","implicit":true,"kind":"Mdef","node":{".class":"Var","flags":["is_inferred"],"fullname":"dns.message.Message.id","name":"id","type":"builtins.int"}},"index":{".class":"SymbolTableNode","implicit":true,"kind":"Mdef","node":{".class":"Var","flags":["explicit_self_type","is_ready","is_inferred"],"fullname":"dns.message.Message.index","name":"index","type":{".class":"TypeAliasType","args":[],"type_ref":"dns.message.IndexType"}}},"is_response":{".class":"SymbolTableNode","kind":"Mdef","node":{".class":"FuncDef","abstract_status":0,"arg_kinds":[0,0],"arg_names":["self","other"],"dataclass_transform_spec":null,"flags":[],"fullname":"dns.message.Message.is_response","name":"is_response","type":{".class":"CallableType","arg_kinds":[0,0],"arg_names":["self","other"],"arg_types":["dns.message.Message","dns.message.Message"],"bound_args":[],"def_extras":{"first_arg":"self"},"fallback":"builtins.function","from_concatenate":false,"implicit":false,"imprecise_arg_kinds":false,"is_ellipsis_args":false,"name":"is_response of Message","ret_type":"builtins.bool","type_guard":null,"unpack_kwargs":false,"variables":[]}}},"keyalgorithm":{".class":"SymbolTableNode","kind":"Mdef","node":{".class":"Decorator","func":{".class":"FuncDef","abstract_status":0,"arg_kinds":[0],"arg_names":["self"],"dataclass_transform_spec":null,"flags":["is_property","is_decorated"],"fullname":"dns.message.Message.keyalgorithm","name":"keyalgorithm","type":{".class":"CallableType","arg_kinds":[0],"arg_names":["self"],"arg_types":["dns.message.Message"],"bound_args":[],"def_extras":{"first_arg":"self"},"fallback":"builtins.function","from_concatenate":false,"implicit":false,"imprecise_arg_kinds":false,"is_ellipsis_args":false,"name":"keyalgorithm of Message","ret_type":{".class":"UnionType","items":["dns.name.Name",{".class":"NoneType"}]},"type_guard":null,"unpack_kwargs":false,"variables":[]}},"is_overload":false,"var":{".class":"Var","flags":["is_initialized_in_class","is_property","is_ready","is_inferred"],"fullname":"dns.message.Message.keyalgorithm","name":"keyalgorithm","type":{".class":"CallableType","arg_kinds":[0],"arg_names":["self"],"arg_types":["dns.message.Message"],"bound_args":[],"def_extras":{"first_arg":"self"},"fallback":"builtins.function","from_concatenate":false,"implicit":false,"imprecise_arg_kinds":false,"is_ellipsis_args":false,"name":"keyalgorithm of Message","ret_type":{".class":"UnionType","items":["dns.name.Name",{".class":"NoneType"}]},"type_guard":null,"unpack_kwargs":false,"variables":[]}}}},"keyname":{".class":"SymbolTableNode","kind":"Mdef","node":{".class":"Decorator","func":{".class":"FuncDef","abstract_status":0,"arg_kinds":[0],"arg_names":["self"],"dataclass_transform_spec":null,"flags":["is_property","is_decorated"],"fullname":"dns.message.Message.keyname","name":"keyname","type":{".class":"CallableType","arg_kinds":[0],"arg_names":["self"],"arg_types":["dns.message.Message"],"bound_args":[],"def_extras":{"first_arg":"self"},"fallback":"builtins.function","from_concatenate":false,"implicit":false,"imprecise_arg_kinds":false,"is_ellipsis_args":false,"name":"keyname of Message","ret_type":{".class":"UnionType","items":["dns.name.Name",{".class":"NoneType"}]},"type_guard":null,"unpack_kwargs":false,"variables":[]}},"is_overload":false,"var":{".class":"Var","flags":["is_initialized_in_class","is_property","is_ready","is_inferred"],"fullname":"dns.message.Message.keyname","name":"keyname","type":{".class":"CallableType","arg_kinds":[0],"arg_names":["self"],"arg_types":["dns.message.Message"],"bound_args":[],"def_extras":{"first_arg":"self"},"fallback":"builtins.function","from_concatenate":false,"implicit":false,"imprecise_arg_kinds":false,"is_ellipsis_args":false,"name":"keyname of Message","ret_type":{".class":"UnionType","items":["dns.name.Name",{".class":"NoneType"}]},"type_guard":null,"unpack_kwargs":false,"variables":[]}}}},"keyring":{".class":"SymbolTableNode","implicit":true,"kind":"Mdef","node":{".class":"Var","flags":["explicit_self_type","is_ready","is_inferred"],"fullname":"dns.message.Message.keyring","name":"keyring","type":{".class":"AnyType","missing_import_name":null,"source_any":null,"type_of_any":2}}},"mac":{".class":"SymbolTableNode","kind":"Mdef","node":{".class":"Decorator","func":{".class":"FuncDef","abstract_status":0,"arg_kinds":[0],"arg_names":["self"],"dataclass_transform_spec":null,"flags":["is_property","is_decorated"],"fullname":"dns.message.Message.mac","name":"mac","type":{".class":"CallableType","arg_kinds":[0],"arg_names":["self"],"arg_types":["dns.message.Message"],"bound_args":[],"def_extras":{"first_arg":"self"},"fallback":"builtins.function","from_concatenate":false,"implicit":false,"imprecise_arg_kinds":false,"is_ellipsis_args":false,"name":"mac of Message","ret_type":{".class":"UnionType","items":["builtins.bytes",{".class":"NoneType"}]},"type_guard":null,"unpack_kwargs":false,"variables":[]}},"is_overload":false,"var":{".class":"Var","flags":["is_initialized_in_class","is_property","is_ready","is_inferred"],"fullname":"dns.message.Message.mac","name":"mac","type":{".class":"CallableType","arg_kinds":[0],"arg_names":["self"],"arg_types":["dns.message.Message"],"bound_args":[],"def_extras":{"first_arg":"self"},"fallback":"builtins.function","from_concatenate":false,"implicit":false,"imprecise_arg_kinds":false,"is_ellipsis_args":false,"name":"mac of Message","ret_type":{".class":"UnionType","items":["builtins.bytes",{".class":"NoneType"}]},"type_guard":null,"unpack_kwargs":false,"variables":[]}}}},"opcode":{".class":"SymbolTableNode","kind":"Mdef","node":{".class":"FuncDef","abstract_status":0,"arg_kinds":[0],"arg_names":["self"],"dataclass_transform_spec":null,"flags":[],"fullname":"dns.message.Message.opcode","name":"opcode","type":{".class":"CallableType","arg_kinds":[0],"arg_names":["self"],"arg_types":["dns.message.Message"],"bound_args":[],"def_extras":{"first_arg":"self"},"fallback":"builtins.function","from_concatenate":false,"implicit":false,"imprecise_arg_kinds":false,"is_ellipsis_args":false,"name":"opcode of Message","ret_type":"dns.opcode.Opcode","type_guard":null,"unpack_kwargs":false,"variables":[]}}},"opt":{".class":"SymbolTableNode","implicit":true,"kind":"Mdef","node":{".class":"Var","flags":["explicit_self_type","is_ready","is_inferred"],"fullname":"dns.message.Message.opt","name":"opt","type":{".class":"UnionType","items":["dns.rrset.RRset",{".class":"NoneType"}]}}},"options":{".class":"SymbolTableNode","kind":"Mdef","node":{".class":"Decorator","func":{".class":"FuncDef","abstract_status":0,"arg_kinds":[0],"arg_names":["self"],"dataclass_transform_spec":null,"flags":["is_property","is_decorated"],"fullname":"dns.message.Message.options","name":"options","type":{".class":"CallableType","arg_kinds":[0],"arg_names":["self"],"arg_types":["dns.message.Message"],"bound_args":[],"def_extras":{"first_arg":"self"},"fallback":"builtins.function","from_concatenate":false,"implicit":false,"imprecise_arg_kinds":false,"is_ellipsis_args":false,"name":"options of Message","ret_type":{".class":"Instance","args":[{".class":"AnyType","missing_import_name":null,"source_any":null,"type_of_any":4}],"type_ref":"builtins.tuple"},"type_guard":null,"unpack_kwargs":false,"variables":[]}},"is_overload":false,"var":{".class":"Var","flags":["is_initialized_in_class","is_property","is_ready","is_inferred"],"fullname":"dns.message.Message.options","name":"options","type":{".class":"CallableType","arg_kinds":[0],"arg_names":["self"],"arg_types":["dns.message.Message"],"bound_args":[],"def_extras":{"first_arg":"self"},"fallback":"builtins.function","from_concatenate":false,"implicit":false,"imprecise_arg_kinds":false,"is_ellipsis_args":false,"name":"options of Message","ret_type":{".class":"Instance","args":[{".class":"AnyType","missing_import_name":null,"source_any":null,"type_of_any":4}],"type_ref":"builtins.tuple"},"type_guard":null,"unpack_kwargs":false,"variables":[]}}}},"origin":{".class":"SymbolTableNode","implicit":true,"kind":"Mdef","node":{".class":"Var","flags":["explicit_self_type","is_ready","is_inferred"],"fullname":"dns.message.Message.origin","name":"origin","type":{".class":"UnionType","items":["dns.name.Name",{".class":"NoneType"}]}}},"pad":{".class":"SymbolTableNode","implicit":true,"kind":"Mdef","node":{".class":"Var","flags":["is_inferred"],"fullname":"dns.message.Message.pad","name":"pad","type":"builtins.int"}},"payload":{".class":"SymbolTableNode","kind":"Mdef","node":{".class":"Decorator","func":{".class":"FuncDef","abstract_status":0,"arg_kinds":[0],"arg_names":["self"],"dataclass_transform_spec":null,"flags":["is_property","is_decorated"],"fullname":"dns.message.Message.payload","name":"payload","type":{".class":"CallableType","arg_kinds":[0],"arg_names":["self"],"arg_types":["dns.message.Message"],"bound_args":[],"def_extras":{"first_arg":"self"},"fallback":"builtins.function","from_concatenate":false,"implicit":false,"imprecise_arg_kinds":false,"is_ellipsis_args":false,"name":"payload of Message","ret_type":"builtins.int","type_guard":null,"unpack_kwargs":false,"variables":[]}},"is_overload":false,"var":{".class":"Var","flags":["is_initialized_in_class","is_property","is_ready","is_inferred"],"fullname":"dns.message.Message.payload","name":"payload","type":{".class":"CallableType","arg_kinds":[0],"arg_names":["self"],"arg_types":["dns.message.Message"],"bound_args":[],"def_extras":{"first_arg":"self"},"fallback":"builtins.function","from_concatenate":false,"implicit":false,"imprecise_arg_kinds":false,"is_ellipsis_args":false,"name":"payload of Message","ret_type":"builtins.int","type_guard":null,"unpack_kwargs":false,"variables":[]}}}},"question":{".class":"SymbolTableNode","kind":"Mdef","node":{".class":"OverloadedFuncDef","flags":["is_property"],"fullname":"dns.message.Message.question","impl":null,"items":[{".class":"Decorator","func":{".class":"FuncDef","abstract_status":0,"arg_kinds":[0],"arg_names":["self"],"dataclass_transform_spec":null,"flags":["is_property","is_overload","is_decorated"],"fullname":"dns.message.Message.question","name":"question","type":{".class":"CallableType","arg_kinds":[0],"arg_names":["self"],"arg_types":["dns.message.Message"],"bound_args":[],"def_extras":{"first_arg":"self"},"fallback":"builtins.function","from_concatenate":false,"implicit":false,"imprecise_arg_kinds":false,"is_ellipsis_args":false,"name":"question of Message","ret_type":{".class":"Instance","args":["dns.rrset.RRset"],"type_ref":"builtins.list"},"type_guard":null,"unpack_kwargs":false,"variables":[]}},"is_overload":true,"var":{".class":"Var","flags":["is_initialized_in_class","is_property","is_settable_property","is_ready","is_inferred"],"fullname":"dns.message.Message.question","name":"question","type":{".class":"CallableType","arg_kinds":[0],"arg_names":["self"],"arg_types":["dns.message.Message"],"bound_args":[],"def_extras":{"first_arg":"self"},"fallback":"builtins.function","from_concatenate":false,"implicit":false,"imprecise_arg_kinds":false,"is_ellipsis_args":false,"name":"question of Message","ret_type":{".class":"Instance","args":["dns.rrset.RRset"],"type_ref":"builtins.list"},"type_guard":null,"unpack_kwargs":false,"variables":[]}}},{".class":"Decorator","func":{".class":"FuncDef","abstract_status":0,"arg_kinds":[0,0],"arg_names":["self","v"],"dataclass_transform_spec":null,"flags":["is_decorated"],"fullname":"dns.message.Message.question","name":"question","type":null},"is_overload":false,"var":{".class":"Var","flags":["is_inferred"],"fullname":"","name":"question","type":null}}],"type":{".class":"Overloaded","items":[{".class":"CallableType","arg_kinds":[0],"arg_names":["self"],"arg_types":["dns.message.Message"],"bound_args":[],"def_extras":{"first_arg":"self"},"fallback":"builtins.function","from_concatenate":false,"implicit":false,"imprecise_arg_kinds":false,"is_ellipsis_args":false,"name":"question of Message","ret_type":{".class":"Instance","args":["dns.rrset.RRset"],"type_ref":"builtins.list"},"type_guard":null,"unpack_kwargs":false,"variables":[]}]}}},"rcode":{".class":"SymbolTableNode","kind":"Mdef","node":{".class":"FuncDef","abstract_status":0,"arg_kinds":[0],"arg_names":["self"],"dataclass_transform_spec":null,"flags":[],"fullname":"dns.message.Message.rcode","name":"rcode","type":{".class":"CallableType","arg_kinds":[0],"arg_names":["self"],"arg_types":["dns.message.Message"],"bound_args":[],"def_extras":{"first_arg":"self"},"fallback":"builtins.function","from_concatenate":false,"implicit":false,"imprecise_arg_kinds":false,"is_ellipsis_args":false,"name":"rcode of Message","ret_type":"dns.rcode.Rcode","type_guard":null,"unpack_kwargs":false,"variables":[]}}},"request_mac":{".class":"SymbolTableNode","implicit":true,"kind":"Mdef","node":{".class":"Var","flags":["is_inferred"],"fullname":"dns.message.Message.request_mac","name":"request_mac","type":"builtins.bytes"}},"request_payload":{".class":"SymbolTableNode","implicit":true,"kind":"Mdef","node":{".class":"Var","flags":["is_inferred"],"fullname":"dns.message.Message.request_payload","name":"request_payload","type":"builtins.int"}},"section_count":{".class":"SymbolTableNode","kind":"Mdef","node":{".class":"FuncDef","abstract_status":0,"arg_kinds":[0,0],"arg_names":["self","section"],"dataclass_transform_spec":null,"flags":[],"fullname":"dns.message.Message.section_count","name":"section_count","type":{".class":"CallableType","arg_kinds":[0,0],"arg_names":["self","section"],"arg_types":["dns.message.Message",{".class":"TypeAliasType","args":[],"type_ref":"dns.message.SectionType"}],"bound_args":[],"def_extras":{"first_arg":"self"},"fallback":"builtins.function","from_concatenate":false,"implicit":false,"imprecise_arg_kinds":false,"is_ellipsis_args":false,"name":"section_count of Message","ret_type":"builtins.int","type_guard":null,"unpack_kwargs":false,"variables":[]}}},"section_from_number":{".class":"SymbolTableNode","kind":"Mdef","node":{".class":"FuncDef","abstract_status":0,"arg_kinds":[0,0],"arg_names":["self","number"],"dataclass_transform_spec":null,"flags":[],"fullname":"dns.message.Message.section_from_number","name":"section_from_number","type":{".class":"CallableType","arg_kinds":[0,0],"arg_names":["self","number"],"arg_types":["dns.message.Message","builtins.int"],"bound_args":[],"def_extras":{"first_arg":"self"},"fallback":"builtins.function","from_concatenate":false,"implicit":false,"imprecise_arg_kinds":false,"is_ellipsis_args":false,"name":"section_from_number of Message","ret_type":{".class":"Instance","args":["dns.rrset.RRset"],"type_ref":"builtins.list"},"type_guard":null,"unpack_kwargs":false,"variables":[]}}},"section_number":{".class":"SymbolTableNode","kind":"Mdef","node":{".class":"FuncDef","abstract_status":0,"arg_kinds":[0,0],"arg_names":["self","section"],"dataclass_transform_spec":null,"flags":[],"fullname":"dns.message.Message.section_number","name":"section_number","type":{".class":"CallableType","arg_kinds":[0,0],"arg_names":["self","section"],"arg_types":["dns.message.Message",{".class":"Instance","args":["dns.rrset.RRset"],"type_ref":"builtins.list"}],"bound_args":[],"def_extras":{"first_arg":"self"},"fallback":"builtins.function","from_concatenate":false,"implicit":false,"imprecise_arg_kinds":false,"is_ellipsis_args":false,"name":"section_number of Message","ret_type":"builtins.int","type_guard":null,"unpack_kwargs":false,"variables":[]}}},"sections":{".class":"SymbolTableNode","implicit":true,"kind":"Mdef","node":{".class":"Var","flags":["explicit_self_type","is_ready","is_inferred"],"fullname":"dns.message.Message.sections","name":"sections","type":{".class":"Instance","args":[{".class":"Instance","args":["dns.rrset.RRset"],"type_ref":"builtins.list"}],"type_ref":"builtins.list"}}},"set_opcode":{".class":"SymbolTableNode","kind":"Mdef","node":{".class":"FuncDef","abstract_status":0,"arg_kinds":[0,0],"arg_names":["self","opcode"],"dataclass_transform_spec":null,"flags":[],"fullname":"dns.message.Message.set_opcode","name":"set_opcode","type":{".class":"CallableType","arg_kinds":[0,0],"arg_names":["self","opcode"],"arg_types":["dns.message.Message","dns.opcode.Opcode"],"bound_args":[],"def_extras":{"first_arg":"self"},"fallback":"builtins.function","from_concatenate":false,"implicit":false,"imprecise_arg_kinds":false,"is_ellipsis_args":false,"name":"set_opcode of Message","ret_type":{".class":"NoneType"},"type_guard":null,"unpack_kwargs":false,"variables":[]}}},"set_rcode":{".class":"SymbolTableNode","kind":"Mdef","node":{".class":"FuncDef","abstract_status":0,"arg_kinds":[0,0],"arg_names":["self","rcode"],"dataclass_transform_spec":null,"flags":[],"fullname":"dns.message.Message.set_rcode","name":"set_rcode","type":{".class":"CallableType","arg_kinds":[0,0],"arg_names":["self","rcode"],"arg_types":["dns.message.Message","dns.rcode.Rcode"],"bound_args":[],"def_extras":{"first_arg":"self"},"fallback":"builtins.function","from_concatenate":false,"implicit":false,"imprecise_arg_kinds":false,"is_ellipsis_args":false,"name":"set_rcode of Message","ret_type":{".class":"NoneType"},"type_guard":null,"unpack_kwargs":false,"variables":[]}}},"time":{".class":"SymbolTableNode","implicit":true,"kind":"Mdef","node":{".class":"Var","flags":["is_inferred"],"fullname":"dns.message.Message.time","name":"time","type":"builtins.float"}},"to_text":{".class":"SymbolTableNode","kind":"Mdef","node":{".class":"FuncDef","abstract_status":0,"arg_kinds":[0,1,1,4],"arg_names":["self","origin","relativize","kw"],"dataclass_transform_spec":null,"flags":[],"fullname":"dns.message.Message.to_text","name":"to_text","type":{".class":"CallableType","arg_kinds":[0,1,1,4],"arg_names":["self","origin","relativize","kw"],"arg_types":["dns.message.Message",{".class":"UnionType","items":["dns.name.Name",{".class":"NoneType"}]},"builtins.bool",{".class":"Instance","args":["builtins.str",{".class":"AnyType","missing_import_name":null,"source_any":null,"type_of_any":2}],"type_ref":"builtins.dict"}],"bound_args":[],"def_extras":{"first_arg":"self"},"fallback":"builtins.function","from_concatenate":false,"implicit":false,"imprecise_arg_kinds":false,"is_ellipsis_args":false,"name":"to_text of Message","ret_type":"builtins.str","type_guard":null,"unpack_kwargs":false,"variables":[]}}},"to_wire":{".class":"SymbolTableNode","kind":"Mdef","node":{".class":"FuncDef","abstract_status":0,"arg_kinds":[0,1,1,1,1,1,1,4],"arg_names":["self","origin","max_size","multi","tsig_ctx","prepend_length","prefer_truncation","kw"],"dataclass_transform_spec":null,"flags":[],"fullname":"dns.message.Message.to_wire","name":"to_wire","type":{".class":"CallableType","arg_kinds":[0,1,1,1,1,1,1,4],"arg_names":["self","origin","max_size","multi","tsig_ctx","prepend_length","prefer_truncation","kw"],"arg_types":["dns.message.Message",{".class":"UnionType","items":["dns.name.Name",{".class":"NoneType"}]},"builtins.int","builtins.bool",{".class":"UnionType","items":[{".class":"AnyType","missing_import_name":null,"source_any":null,"type_of_any":2},{".class":"NoneType"}]},"builtins.bool","builtins.bool",{".class":"Instance","args":["builtins.str",{".class":"AnyType","missing_import_name":null,"source_any":null,"type_of_any":2}],"type_ref":"builtins.dict"}],"bound_args":[],"def_extras":{"first_arg":"self"},"fallback":"builtins.function","from_concatenate":false,"implicit":false,"imprecise_arg_kinds":false,"is_ellipsis_args":false,"name":"to_wire of Message","ret_type":"builtins.bytes","type_guard":null,"unpack_kwargs":false,"variables":[]}}},"tsig":{".class":"SymbolTableNode","implicit":true,"kind":"Mdef","node":{".class":"Var","flags":["explicit_self_type","is_ready","is_inferred"],"fullname":"dns.message.Message.tsig","name":"tsig","type":{".class":"UnionType","items":["dns.rrset.RRset",{".class":"NoneType"}]}}},"tsig_ctx":{".class":"SymbolTableNode","implicit":true,"kind":"Mdef","node":{".class":"Var","flags":["explicit_self_type","is_ready","is_inferred"],"fullname":"dns.message.Message.tsig_ctx","name":"tsig_ctx","type":{".class":"UnionType","items":[{".class":"AnyType","missing_import_name":null,"source_any":null,"type_of_any":2},{".class":"NoneType"}]}}},"tsig_error":{".class":"SymbolTableNode","kind":"Mdef","node":{".class":"Decorator","func":{".class":"FuncDef","abstract_status":0,"arg_kinds":[0],"arg_names":["self"],"dataclass_transform_spec":null,"flags":["is_property","is_decorated"],"fullname":"dns.message.Message.tsig_error","name":"tsig_error","type":{".class":"CallableType","arg_kinds":[0],"arg_names":["self"],"arg_types":["dns.message.Message"],"bound_args":[],"def_extras":{"first_arg":"self"},"fallback":"builtins.function","from_concatenate":false,"implicit":false,"imprecise_arg_kinds":false,"is_ellipsis_args":false,"name":"tsig_error of Message","ret_type":{".class":"UnionType","items":["builtins.int",{".class":"NoneType"}]},"type_guard":null,"unpack_kwargs":false,"variables":[]}},"is_overload":false,"var":{".class":"Var","flags":["is_initialized_in_class","is_property","is_ready","is_inferred"],"fullname":"dns.message.Message.tsig_error","name":"tsig_error","type":{".class":"CallableType","arg_kinds":[0],"arg_names":["self"],"arg_types":["dns.message.Message"],"bound_args":[],"def_extras":{"first_arg":"self"},"fallback":"builtins.function","from_concatenate":false,"implicit":false,"imprecise_arg_kinds":false,"is_ellipsis_args":false,"name":"tsig_error of Message","ret_type":{".class":"UnionType","items":["builtins.int",{".class":"NoneType"}]},"type_guard":null,"unpack_kwargs":false,"variables":[]}}}},"use_edns":{".class":"SymbolTableNode","kind":"Mdef","node":{".class":"FuncDef","abstract_status":0,"arg_kinds":[0,1,1,1,1,1,1],"arg_names":["self","edns","ednsflags","payload","request_payload","options","pad"],"dataclass_transform_spec":null,"flags":[],"fullname":"dns.message.Message.use_edns","name":"use_edns","type":{".class":"CallableType","arg_kinds":[0,1,1,1,1,1,1],"arg_names":["self","edns","ednsflags","payload","request_payload","options","pad"],"arg_types":["dns.message.Message",{".class":"UnionType","items":["builtins.int","builtins.bool",{".class":"NoneType"}]},"builtins.int","builtins.int",{".class":"UnionType","items":["builtins.int",{".class":"NoneType"}]},{".class":"UnionType","items":[{".class":"Instance","args":["dns.edns.Option"],"type_ref":"builtins.list"},{".class":"NoneType"}]},"builtins.int"],"bound_args":[],"def_extras":{"first_arg":"self"},"fallback":"builtins.function","from_concatenate":false,"implicit":false,"imprecise_arg_kinds":false,"is_ellipsis_args":false,"name":"use_edns of Message","ret_type":{".class":"NoneType"},"type_guard":null,"unpack_kwargs":false,"variables":[]}}},"use_tsig":{".class":"SymbolTableNode","kind":"Mdef","node":{".class":"FuncDef","abstract_status":0,"arg_kinds":[0,0,1,1,1,1,1,1],"arg_names":["self","keyring","keyname","fudge","original_id","tsig_error","other_data","algorithm"],"dataclass_transform_spec":null,"flags":[],"fullname":"dns.message.Message.use_tsig","name":"use_tsig","type":{".class":"CallableType","arg_kinds":[0,0,1,1,1,1,1,1],"arg_names":["self","keyring","keyname","fudge","original_id","tsig_error","other_data","algorithm"],"arg_types":["dns.message.Message",{".class":"AnyType","missing_import_name":null,"source_any":null,"type_of_any":2},{".class":"UnionType","items":["dns.name.Name","builtins.str",{".class":"NoneType"}]},"builtins.int",{".class":"UnionType","items":["builtins.int",{".class":"NoneType"}]},"builtins.int","builtins.bytes",{".class":"UnionType","items":["dns.name.Name","builtins.str"]}],"bound_args":[],"def_extras":{"first_arg":"self"},"fallback":"builtins.function","from_concatenate":false,"implicit":false,"imprecise_arg_kinds":false,"is_ellipsis_args":false,"name":"use_tsig of Message","ret_type":{".class":"NoneType"},"type_guard":null,"unpack_kwargs":false,"variables":[]}}},"want_dnssec":{".class":"SymbolTableNode","kind":"Mdef","node":{".class":"FuncDef","abstract_status":0,"arg_kinds":[0,1],"arg_names":["self","wanted"],"dataclass_transform_spec":null,"flags":[],"fullname":"dns.message.Message.want_dnssec","name":"want_dnssec","type":{".class":"CallableType","arg_kinds":[0,1],"arg_names":["self","wanted"],"arg_types":["dns.message.Message","builtins.bool"],"bound_args":[],"def_extras":{"first_arg":"self"},"fallback":"builtins.function","from_concatenate":false,"implicit":false,"imprecise_arg_kinds":false,"is_ellipsis_args":false,"name":"want_dnssec of Message","ret_type":{".class":"NoneType"},"type_guard":null,"unpack_kwargs":false,"variables":[]}}},"xfr":{".class":"SymbolTableNode","implicit":true,"kind":"Mdef","node":{".class":"Var","flags":["is_inferred"],"fullname":"dns.message.Message.xfr","name":"xfr","type":"builtins.bool"}}},"self_type":{".class":"TypeVarType","default":{".class":"AnyType","missing_import_name":null,"source_any":null,"type_of_any":4},"fullname":"dns.message.Message.Self","id":0,"name":"Self","namespace":"","upper_bound":"dns.message.Message","values":[],"variance":0},"slots":null,"tuple_type":null,"type_vars":[],"typeddict_type":null}},"MessageError":{".class":"SymbolTableNode","kind":"Gdef","node":{".class":"TypeInfo","_promote":[],"abstract_attributes":[],"alt_promote":null,"bases":["builtins.object"],"dataclass_transform_spec":null,"declared_metaclass":null,"defn":{".class":"ClassDef","fullname":"dns.message.MessageError","name":"MessageError","type_vars":[]},"deletable_attributes":[],"flags":[],"fullname":"dns.message.MessageError","has_param_spec_type":false,"metaclass_type":null,"metadata":{},"module_name":"dns.message","mro":["dns.message.MessageError","builtins.object"],"names":{".class":"SymbolTable","__init__":{".class":"SymbolTableNode","kind":"Mdef","node":{".class":"FuncDef","abstract_status":0,"arg_kinds":[0,0,0],"arg_names":["self","exception","offset"],"dataclass_transform_spec":null,"flags":[],"fullname":"dns.message.MessageError.__init__","name":"__init__","type":{".class":"CallableType","arg_kinds":[0,0,0],"arg_names":["self","exception","offset"],"arg_types":["dns.message.MessageError","builtins.Exception","builtins.int"],"bound_args":[],"def_extras":{"first_arg":"self"},"fallback":"builtins.function","from_concatenate":false,"implicit":false,"imprecise_arg_kinds":false,"is_ellipsis_args":false,"name":"__init__ of MessageError","ret_type":{".class":"NoneType"},"type_guard":null,"unpack_kwargs":false,"variables":[]}}},"exception":{".class":"SymbolTableNode","implicit":true,"kind":"Mdef","node":{".class":"Var","flags":["is_inferred"],"fullname":"dns.message.MessageError.exception","name":"exception","type":"builtins.Exception"}},"offset":{".class":"SymbolTableNode","implicit":true,"kind":"Mdef","node":{".class":"Var","flags":["is_inferred"],"fullname":"dns.message.MessageError.offset","name":"offset","type":"builtins.int"}}},"self_type":{".class":"TypeVarType","default":{".class":"AnyType","missing_import_name":null,"source_any":null,"type_of_any":4},"fullname":"dns.message.MessageError.Self","id":0,"name":"Self","namespace":"","upper_bound":"dns.message.MessageError","values":[],"variance":0},"slots":null,"tuple_type":null,"type_vars":[],"typeddict_type":null}},"MessageSection":{".class":"SymbolTableNode","kind":"Gdef","node":{".class":"TypeInfo","_promote":[],"abstract_attributes":[],"alt_promote":null,"bases":["dns.enum.IntEnum"],"dataclass_transform_spec":null,"declared_metaclass":null,"defn":{".class":"ClassDef","fullname":"dns.message.MessageSection","name":"MessageSection","type_vars":[]},"deletable_attributes":[],"flags":["is_enum"],"fullname":"dns.message.MessageSection","has_param_spec_type":false,"metaclass_type":"enum.EnumMeta","metadata":{},"module_name":"dns.message","mro":["dns.message.MessageSection","dns.enum.IntEnum","enum.IntEnum","builtins.int","enum.ReprEnum","enum.Enum","builtins.object"],"names":{".class":"SymbolTable","ADDITIONAL":{".class":"SymbolTableNode","kind":"Mdef","node":{".class":"Var","flags":["is_initialized_in_class","is_final","is_ready","is_inferred","has_explicit_value"],"fullname":"dns.message.MessageSection.ADDITIONAL","name":"ADDITIONAL","type":{".class":"Instance","args":[],"last_known_value":{".class":"LiteralType","fallback":"builtins.int","value":3},"type_ref":"builtins.int"}}},"ANSWER":{".class":"SymbolTableNode","kind":"Mdef","node":{".class":"Var","flags":["is_initialized_in_class","is_final","is_ready","is_inferred","has_explicit_value"],"fullname":"dns.message.MessageSection.ANSWER","name":"ANSWER","type":{".class":"Instance","args":[],"last_known_value":{".class":"LiteralType","fallback":"builtins.int","value":1},"type_ref":"builtins.int"}}},"AUTHORITY":{".class":"SymbolTableNode","kind":"Mdef","node":{".class":"Var","flags":["is_initialized_in_class","is_final","is_ready","is_inferred","has_explicit_value"],"fullname":"dns.message.MessageSection.AUTHORITY","name":"AUTHORITY","type":{".class":"Instance","args":[],"last_known_value":{".class":"LiteralType","fallback":"builtins.int","value":2},"type_ref":"builtins.int"}}},"QUESTION":{".class":"SymbolTableNode","kind":"Mdef","node":{".class":"Var","flags":["is_initialized_in_class","is_final","is_ready","is_inferred","has_explicit_value"],"fullname":"dns.message.MessageSection.QUESTION","name":"QUESTION","type":{".class":"Instance","args":[],"last_known_value":{".class":"LiteralType","fallback":"builtins.int","value":0},"type_ref":"builtins.int"}}},"_maximum":{".class":"SymbolTableNode","kind":"Mdef","node":{".class":"Decorator","func":{".class":"FuncDef","abstract_status":0,"arg_kinds":[0],"arg_names":["cls"],"dataclass_transform_spec":null,"flags":["is_class","is_decorated"],"fullname":"dns.message.MessageSection._maximum","name":"_maximum","type":null},"is_overload":false,"var":{".class":"Var","flags":["is_initialized_in_class","is_classmethod","is_ready","is_inferred"],"fullname":"dns.message.MessageSection._maximum","name":"_maximum","type":{".class":"CallableType","arg_kinds":[0],"arg_names":["cls"],"arg_types":[{".class":"TypeType","item":"dns.message.MessageSection"}],"bound_args":[],"def_extras":{"first_arg":"cls"},"fallback":"builtins.function","from_concatenate":false,"implicit":true,"imprecise_arg_kinds":false,"is_ellipsis_args":false,"name":"_maximum of MessageSection","ret_type":{".class":"AnyType","missing_import_name":null,"source_any":null,"type_of_any":1},"type_guard":null,"unpack_kwargs":false,"variables":[]}}}}},"self_type":{".class":"TypeVarType","default":{".class":"AnyType","missing_import_name":null,"source_any":null,"type_of_any":4},"fullname":"dns.message.MessageSection.Self","id":0,"name":"Self","namespace":"","upper_bound":"dns.message.MessageSection","values":[],"variance":0},"slots":null,"tuple_type":null,"type_vars":[],"typeddict_type":null}},"NoPreviousName":{".class":"SymbolTableNode","kind":"Gdef","node":{".class":"TypeInfo","_promote":[],"abstract_attributes":[],"alt_promote":null,"bases":["dns.exception.SyntaxError"],"dataclass_transform_spec":null,"declared_metaclass":null,"defn":{".class":"ClassDef","fullname":"dns.message.NoPreviousName","name":"NoPreviousName","type_vars":[]},"deletable_attributes":[],"flags":[],"fullname":"dns.message.NoPreviousName","has_param_spec_type":false,"metaclass_type":null,"metadata":{},"module_name":"dns.message","mro":["dns.message.NoPreviousName","dns.exception.SyntaxError","dns.exception.DNSException","builtins.Exception","builtins.BaseException","builtins.object"],"names":{".class":"SymbolTable"},"self_type":{".class":"TypeVarType","default":{".class":"AnyType","missing_import_name":null,"source_any":null,"type_of_any":4},"fullname":"dns.message.NoPreviousName.Self","id":0,"name":"Self","namespace":"","upper_bound":"dns.message.NoPreviousName","values":[],"variance":0},"slots":null,"tuple_type":null,"type_vars":[],"typeddict_type":null}},"NotQueryResponse":{".class":"SymbolTableNode","kind":"Gdef","node":{".class":"TypeInfo","_promote":[],"abstract_attributes":[],"alt_promote":null,"bases":["dns.exception.DNSException"],"dataclass_transform_spec":null,"declared_metaclass":null,"defn":{".class":"ClassDef","fullname":"dns.message.NotQueryResponse","name":"NotQueryResponse","type_vars":[]},"deletable_attributes":[],"flags":[],"fullname":"dns.message.NotQueryResponse","has_param_spec_type":false,"metaclass_type":null,"metadata":{},"module_name":"dns.message","mro":["dns.message.NotQueryResponse","dns.exception.DNSException","builtins.Exception","builtins.BaseException","builtins.object"],"names":{".class":"SymbolTable"},"self_type":{".class":"TypeVarType","default":{".class":"AnyType","missing_import_name":null,"source_any":null,"type_of_any":4},"fullname":"dns.message.NotQueryResponse.Self","id":0,"name":"Self","namespace":"","upper_bound":"dns.message.NotQueryResponse","values":[],"variance":0},"slots":null,"tuple_type":null,"type_vars":[],"typeddict_type":null}},"Optional":{".class":"SymbolTableNode","cross_ref":"typing.Optional","kind":"Gdef"},"QUESTION":{".class":"SymbolTableNode","kind":"Gdef","node":{".class":"Var","flags":["is_inferred","has_explicit_value"],"fullname":"dns.message.QUESTION","name":"QUESTION","type":"dns.message.MessageSection"}},"QueryMessage":{".class":"SymbolTableNode","kind":"Gdef","node":{".class":"TypeInfo","_promote":[],"abstract_attributes":[],"alt_promote":null,"bases":["dns.message.Message"],"dataclass_transform_spec":null,"declared_metaclass":null,"defn":{".class":"ClassDef","fullname":"dns.message.QueryMessage","name":"QueryMessage","type_vars":[]},"deletable_attributes":[],"flags":[],"fullname":"dns.message.QueryMessage","has_param_spec_type":false,"metaclass_type":null,"metadata":{},"module_name":"dns.message","mro":["dns.message.QueryMessage","dns.message.Message","builtins.object"],"names":{".class":"SymbolTable","canonical_name":{".class":"SymbolTableNode","kind":"Mdef","node":{".class":"FuncDef","abstract_status":0,"arg_kinds":[0],"arg_names":["self"],"dataclass_transform_spec":null,"flags":[],"fullname":"dns.message.QueryMessage.canonical_name","name":"canonical_name","type":{".class":"CallableType","arg_kinds":[0],"arg_names":["self"],"arg_types":["dns.message.QueryMessage"],"bound_args":[],"def_extras":{"first_arg":"self"},"fallback":"builtins.function","from_concatenate":false,"implicit":false,"imprecise_arg_kinds":false,"is_ellipsis_args":false,"name":"canonical_name of QueryMessage","ret_type":"dns.name.Name","type_guard":null,"unpack_kwargs":false,"variables":[]}}},"resolve_chaining":{".class":"SymbolTableNode","kind":"Mdef","node":{".class":"FuncDef","abstract_status":0,"arg_kinds":[0],"arg_names":["self"],"dataclass_transform_spec":null,"flags":[],"fullname":"dns.message.QueryMessage.resolve_chaining","name":"resolve_chaining","type":{".class":"CallableType","arg_kinds":[0],"arg_names":["self"],"arg_types":["dns.message.QueryMessage"],"bound_args":[],"def_extras":{"first_arg":"self"},"fallback":"builtins.function","from_concatenate":false,"implicit":false,"imprecise_arg_kinds":false,"is_ellipsis_args":false,"name":"resolve_chaining of QueryMessage","ret_type":"dns.message.ChainingResult","type_guard":null,"unpack_kwargs":false,"variables":[]}}}},"self_type":{".class":"TypeVarType","default":{".class":"AnyType","missing_import_name":null,"source_any":null,"type_of_any":4},"fullname":"dns.message.QueryMessage.Self","id":0,"name":"Self","namespace":"","upper_bound":"dns.message.QueryMessage","values":[],"variance":0},"slots":null,"tuple_type":null,"type_vars":[],"typeddict_type":null}},"SectionType":{".class":"SymbolTableNode","kind":"Gdef","node":{".class":"TypeAlias","alias_tvars":[],"column":0,"fullname":"dns.message.SectionType","line":137,"no_args":false,"normalized":false,"target":{".class":"UnionType","items":["builtins.int","builtins.str",{".class":"Instance","args":["dns.rrset.RRset"],"type_ref":"builtins.list"}]}}},"ShortHeader":{".class":"SymbolTableNode","kind":"Gdef","node":{".class":"TypeInfo","_promote":[],"abstract_attributes":[],"alt_promote":null,"bases":["dns.exception.FormError"],"dataclass_transform_spec":null,"declared_metaclass":null,"defn":{".class":"ClassDef","fullname":"dns.message.ShortHeader","name":"ShortHeader","type_vars":[]},"deletable_attributes":[],"flags":[],"fullname":"dns.message.ShortHeader","has_param_spec_type":false,"metaclass_type":null,"metadata":{},"module_name":"dns.message","mro":["dns.message.ShortHeader","dns.exception.FormError","dns.exception.DNSException","builtins.Exception","builtins.BaseException","builtins.object"],"names":{".class":"SymbolTable"},"self_type":{".class":"TypeVarType","default":{".class":"AnyType","missing_import_name":null,"source_any":null,"type_of_any":4},"fullname":"dns.message.ShortHeader.Self","id":0,"name":"Self","namespace":"","upper_bound":"dns.message.ShortHeader","values":[],"variance":0},"slots":null,"tuple_type":null,"type_vars":[],"typeddict_type":null}},"TrailingJunk":{".class":"SymbolTableNode","kind":"Gdef","node":{".class":"TypeInfo","_promote":[],"abstract_attributes":[],"alt_promote":null,"bases":["dns.exception.FormError"],"dataclass_transform_spec":null,"declared_metaclass":null,"defn":{".class":"ClassDef","fullname":"dns.message.TrailingJunk","name":"TrailingJunk","type_vars":[]},"deletable_attributes":[],"flags":[],"fullname":"dns.message.TrailingJunk","has_param_spec_type":false,"metaclass_type":null,"metadata":{},"module_name":"dns.message","mro":["dns.message.TrailingJunk","dns.exception.FormError","dns.exception.DNSException","builtins.Exception","builtins.BaseException","builtins.object"],"names":{".class":"SymbolTable"},"self_type":{".class":"TypeVarType","default":{".class":"AnyType","missing_import_name":null,"source_any":null,"type_of_any":4},"fullname":"dns.message.TrailingJunk.Self","id":0,"name":"Self","namespace":"","upper_bound":"dns.message.TrailingJunk","values":[],"variance":0},"slots":null,"tuple_type":null,"type_vars":[],"typeddict_type":null}},"Truncated":{".class":"SymbolTableNode","kind":"Gdef","node":{".class":"TypeInfo","_promote":[],"abstract_attributes":[],"alt_promote":null,"bases":["dns.exception.DNSException"],"dataclass_transform_spec":null,"declared_metaclass":null,"defn":{".class":"ClassDef","fullname":"dns.message.Truncated","name":"Truncated","type_vars":[]},"deletable_attributes":[],"flags":[],"fullname":"dns.message.Truncated","has_param_spec_type":false,"metaclass_type":null,"metadata":{},"module_name":"dns.message","mro":["dns.message.Truncated","dns.exception.DNSException","builtins.Exception","builtins.BaseException","builtins.object"],"names":{".class":"SymbolTable","__init__":{".class":"SymbolTableNode","kind":"Mdef","node":{".class":"FuncDef","abstract_status":0,"arg_kinds":[0,2,4],"arg_names":["self","args","kwargs"],"dataclass_transform_spec":null,"flags":[],"fullname":"dns.message.Truncated.__init__","name":"__init__","type":null}},"message":{".class":"SymbolTableNode","kind":"Mdef","node":{".class":"FuncDef","abstract_status":0,"arg_kinds":[0],"arg_names":["self"],"dataclass_transform_spec":null,"flags":[],"fullname":"dns.message.Truncated.message","name":"message","type":null}},"supp_kwargs":{".class":"SymbolTableNode","kind":"Mdef","node":{".class":"Var","flags":["is_initialized_in_class","is_inferred","has_explicit_value"],"fullname":"dns.message.Truncated.supp_kwargs","name":"supp_kwargs","type":{".class":"Instance","args":["builtins.str"],"type_ref":"builtins.set"}}}},"self_type":{".class":"TypeVarType","default":{".class":"AnyType","missing_import_name":null,"source_any":null,"type_of_any":4},"fullname":"dns.message.Truncated.Self","id":0,"name":"Self","namespace":"","upper_bound":"dns.message.Truncated","values":[],"variance":0},"slots":null,"tuple_type":null,"type_vars":[],"typeddict_type":null}},"Tuple":{".class":"SymbolTableNode","cross_ref":"typing.Tuple","kind":"Gdef"},"Union":{".class":"SymbolTableNode","cross_ref":"typing.Union","kind":"Gdef"},"UnknownHeaderField":{".class":"SymbolTableNode","kind":"Gdef","node":{".class":"TypeInfo","_promote":[],"abstract_attributes":[],"alt_promote":null,"bases":["dns.exception.DNSException"],"dataclass_transform_spec":null,"declared_metaclass":null,"defn":{".class":"ClassDef","fullname":"dns.message.UnknownHeaderField","name":"UnknownHeaderField","type_vars":[]},"deletable_attributes":[],"flags":[],"fullname":"dns.message.UnknownHeaderField","has_param_spec_type":false,"metaclass_type":null,"metadata":{},"module_name":"dns.message","mro":["dns.message.UnknownHeaderField","dns.exception.DNSException","builtins.Exception","builtins.BaseException","builtins.object"],"names":{".class":"SymbolTable"},"self_type":{".class":"TypeVarType","default":{".class":"AnyType","missing_import_name":null,"source_any":null,"type_of_any":4},"fullname":"dns.message.UnknownHeaderField.Self","id":0,"name":"Self","namespace":"","upper_bound":"dns.message.UnknownHeaderField","values":[],"variance":0},"slots":null,"tuple_type":null,"type_vars":[],"typeddict_type":null}},"UnknownTSIGKey":{".class":"SymbolTableNode","kind":"Gdef","node":{".class":"TypeInfo","_promote":[],"abstract_attributes":[],"alt_promote":null,"bases":["dns.exception.DNSException"],"dataclass_transform_spec":null,"declared_metaclass":null,"defn":{".class":"ClassDef","fullname":"dns.message.UnknownTSIGKey","name":"UnknownTSIGKey","type_vars":[]},"deletable_attributes":[],"flags":[],"fullname":"dns.message.UnknownTSIGKey","has_param_spec_type":false,"metaclass_type":null,"metadata":{},"module_name":"dns.message","mro":["dns.message.UnknownTSIGKey","dns.exception.DNSException","builtins.Exception","builtins.BaseException","builtins.object"],"names":{".class":"SymbolTable"},"self_type":{".class":"TypeVarType","default":{".class":"AnyType","missing_import_name":null,"source_any":null,"type_of_any":4},"fullname":"dns.message.UnknownTSIGKey.Self","id":0,"name":"Self","namespace":"","upper_bound":"dns.message.UnknownTSIGKey","values":[],"variance":0},"slots":null,"tuple_type":null,"type_vars":[],"typeddict_type":null}},"_TextReader":{".class":"SymbolTableNode","kind":"Gdef","node":{".class":"TypeInfo","_promote":[],"abstract_attributes":[],"alt_promote":null,"bases":["builtins.object"],"dataclass_transform_spec":null,"declared_metaclass":null,"defn":{".class":"ClassDef","fullname":"dns.message._TextReader","name":"_TextReader","type_vars":[]},"deletable_attributes":[],"flags":[],"fullname":"dns.message._TextReader","has_param_spec_type":false,"metaclass_type":null,"metadata":{},"module_name":"dns.message","mro":["dns.message._TextReader","builtins.object"],"names":{".class":"SymbolTable","__init__":{".class":"SymbolTableNode","kind":"Mdef","node":{".class":"FuncDef","abstract_status":0,"arg_kinds":[0,0,0,1,1,1,1],"arg_names":["self","text","idna_codec","one_rr_per_rrset","origin","relativize","relativize_to"],"dataclass_transform_spec":null,"flags":[],"fullname":"dns.message._TextReader.__init__","name":"__init__","type":null}},"_header_line":{".class":"SymbolTableNode","kind":"Mdef","node":{".class":"FuncDef","abstract_status":0,"arg_kinds":[0,0],"arg_names":["self","_"],"dataclass_transform_spec":null,"flags":[],"fullname":"dns.message._TextReader._header_line","name":"_header_line","type":null}},"_make_message":{".class":"SymbolTableNode","kind":"Mdef","node":{".class":"FuncDef","abstract_status":0,"arg_kinds":[0],"arg_names":["self"],"dataclass_transform_spec":null,"flags":[],"fullname":"dns.message._TextReader._make_message","name":"_make_message","type":null}},"_question_line":{".class":"SymbolTableNode","kind":"Mdef","node":{".class":"FuncDef","abstract_status":0,"arg_kinds":[0,0],"arg_names":["self","section_number"],"dataclass_transform_spec":null,"flags":[],"fullname":"dns.message._TextReader._question_line","name":"_question_line","type":null}},"_rr_line":{".class":"SymbolTableNode","kind":"Mdef","node":{".class":"FuncDef","abstract_status":0,"arg_kinds":[0,0],"arg_names":["self","section_number"],"dataclass_transform_spec":null,"flags":[],"fullname":"dns.message._TextReader._rr_line","name":"_rr_line","type":null}},"edns":{".class":"SymbolTableNode","implicit":true,"kind":"Mdef","node":{".class":"Var","flags":["is_inferred"],"fullname":"dns.message._TextReader.edns","name":"edns","type":{".class":"AnyType","missing_import_name":null,"source_any":null,"type_of_any":1}}},"ednsflags":{".class":"SymbolTableNode","implicit":true,"kind":"Mdef","node":{".class":"Var","flags":["is_inferred"],"fullname":"dns.message._TextReader.ednsflags","name":"ednsflags","type":{".class":"AnyType","missing_import_name":null,"source_any":null,"type_of_any":1}}},"flags":{".class":"SymbolTableNode","implicit":true,"kind":"Mdef","node":{".class":"Var","flags":["is_inferred"],"fullname":"dns.message._TextReader.flags","name":"flags","type":{".class":"AnyType","missing_import_name":null,"source_any":null,"type_of_any":1}}},"id":{".class":"SymbolTableNode","implicit":true,"kind":"Mdef","node":{".class":"Var","flags":["is_inferred"],"fullname":"dns.message._TextReader.id","name":"id","type":{".class":"AnyType","missing_import_name":null,"source_any":null,"type_of_any":1}}},"last_name":{".class":"SymbolTableNode","implicit":true,"kind":"Mdef","node":{".class":"Var","flags":["is_inferred"],"fullname":"dns.message._TextReader.last_name","name":"last_name","type":{".class":"AnyType","missing_import_name":null,"source_any":null,"type_of_any":1}}},"message":{".class":"SymbolTableNode","implicit":true,"kind":"Mdef","node":{".class":"Var","flags":["is_inferred"],"fullname":"dns.message._TextReader.message","name":"message","type":{".class":"AnyType","missing_import_name":null,"source_any":null,"type_of_any":1}}},"one_rr_per_rrset":{".class":"SymbolTableNode","implicit":true,"kind":"Mdef","node":{".class":"Var","flags":["is_inferred"],"fullname":"dns.message._TextReader.one_rr_per_rrset","name":"one_rr_per_rrset","type":{".class":"AnyType","missing_import_name":null,"source_any":null,"type_of_any":1}}},"opcode":{".class":"SymbolTableNode","implicit":true,"kind":"Mdef","node":{".class":"Var","flags":["is_inferred"],"fullname":"dns.message._TextReader.opcode","name":"opcode","type":{".class":"AnyType","missing_import_name":null,"source_any":null,"type_of_any":1}}},"origin":{".class":"SymbolTableNode","implicit":true,"kind":"Mdef","node":{".class":"Var","flags":["is_inferred"],"fullname":"dns.message._TextReader.origin","name":"origin","type":{".class":"AnyType","missing_import_name":null,"source_any":null,"type_of_any":1}}},"payload":{".class":"SymbolTableNode","implicit":true,"kind":"Mdef","node":{".class":"Var","flags":["is_inferred"],"fullname":"dns.message._TextReader.payload","name":"payload","type":{".class":"AnyType","missing_import_name":null,"source_any":null,"type_of_any":1}}},"rcode":{".class":"SymbolTableNode","implicit":true,"kind":"Mdef","node":{".class":"Var","flags":["is_inferred"],"fullname":"dns.message._TextReader.rcode","name":"rcode","type":{".class":"AnyType","missing_import_name":null,"source_any":null,"type_of_any":1}}},"read":{".class":"SymbolTableNode","kind":"Mdef","node":{".class":"FuncDef","abstract_status":0,"arg_kinds":[0],"arg_names":["self"],"dataclass_transform_spec":null,"flags":[],"fullname":"dns.message._TextReader.read","name":"read","type":null}},"relativize":{".class":"SymbolTableNode","implicit":true,"kind":"Mdef","node":{".class":"Var","flags":["is_inferred"],"fullname":"dns.message._TextReader.relativize","name":"relativize","type":{".class":"AnyType","missing_import_name":null,"source_any":null,"type_of_any":1}}},"relativize_to":{".class":"SymbolTableNode","implicit":true,"kind":"Mdef","node":{".class":"Var","flags":["is_inferred"],"fullname":"dns.message._TextReader.relativize_to","name":"relativize_to","type":{".class":"AnyType","missing_import_name":null,"source_any":null,"type_of_any":1}}},"tok":{".class":"SymbolTableNode","implicit":true,"kind":"Mdef","node":{".class":"Var","flags":["is_inferred"],"fullname":"dns.message._TextReader.tok","name":"tok","type":{".class":"AnyType","missing_import_name":null,"source_any":null,"type_of_any":1}}}},"self_type":{".class":"TypeVarType","default":{".class":"AnyType","missing_import_name":null,"source_any":null,"type_of_any":4},"fullname":"dns.message._TextReader.Self","id":0,"name":"Self","namespace":"","upper_bound":"dns.message._TextReader","values":[],"variance":0},"slots":null,"tuple_type":null,"type_vars":[],"typeddict_type":null}},"_WireReader":{".class":"SymbolTableNode","kind":"Gdef","node":{".class":"TypeInfo","_promote":[],"abstract_attributes":[],"alt_promote":null,"bases":["builtins.object"],"dataclass_transform_spec":null,"declared_metaclass":null,"defn":{".class":"ClassDef","fullname":"dns.message._WireReader","name":"_WireReader","type_vars":[]},"deletable_attributes":[],"flags":[],"fullname":"dns.message._WireReader","has_param_spec_type":false,"metaclass_type":null,"metadata":{},"module_name":"dns.message","mro":["dns.message._WireReader","builtins.object"],"names":{".class":"SymbolTable","__init__":{".class":"SymbolTableNode","kind":"Mdef","node":{".class":"FuncDef","abstract_status":0,"arg_kinds":[0,0,0,1,1,1,1,1,1],"arg_names":["self","wire","initialize_message","question_only","one_rr_per_rrset","ignore_trailing","keyring","multi","continue_on_error"],"dataclass_transform_spec":null,"flags":[],"fullname":"dns.message._WireReader.__init__","name":"__init__","type":null}},"_add_error":{".class":"SymbolTableNode","kind":"Mdef","node":{".class":"FuncDef","abstract_status":0,"arg_kinds":[0,0],"arg_names":["self","e"],"dataclass_transform_spec":null,"flags":[],"fullname":"dns.message._WireReader._add_error","name":"_add_error","type":null}},"_get_question":{".class":"SymbolTableNode","kind":"Mdef","node":{".class":"FuncDef","abstract_status":0,"arg_kinds":[0,0,0],"arg_names":["self","section_number","qcount"],"dataclass_transform_spec":null,"flags":[],"fullname":"dns.message._WireReader._get_question","name":"_get_question","type":null}},"_get_section":{".class":"SymbolTableNode","kind":"Mdef","node":{".class":"FuncDef","abstract_status":0,"arg_kinds":[0,0,0],"arg_names":["self","section_number","count"],"dataclass_transform_spec":null,"flags":[],"fullname":"dns.message._WireReader._get_section","name":"_get_section","type":null}},"continue_on_error":{".class":"SymbolTableNode","implicit":true,"kind":"Mdef","node":{".class":"Var","flags":["is_inferred"],"fullname":"dns.message._WireReader.continue_on_error","name":"continue_on_error","type":{".class":"AnyType","missing_import_name":null,"source_any":null,"type_of_any":1}}},"errors":{".class":"SymbolTableNode","implicit":true,"kind":"Mdef","node":{".class":"Var","flags":["is_inferred"],"fullname":"dns.message._WireReader.errors","name":"errors","type":{".class":"AnyType","missing_import_name":null,"source_any":null,"type_of_any":1}}},"ignore_trailing":{".class":"SymbolTableNode","implicit":true,"kind":"Mdef","node":{".class":"Var","flags":["is_inferred"],"fullname":"dns.message._WireReader.ignore_trailing","name":"ignore_trailing","type":{".class":"AnyType","missing_import_name":null,"source_any":null,"type_of_any":1}}},"initialize_message":{".class":"SymbolTableNode","implicit":true,"kind":"Mdef","node":{".class":"Var","flags":["is_inferred"],"fullname":"dns.message._WireReader.initialize_message","name":"initialize_message","type":{".class":"AnyType","missing_import_name":null,"source_any":null,"type_of_any":1}}},"keyring":{".class":"SymbolTableNode","implicit":true,"kind":"Mdef","node":{".class":"Var","flags":["is_inferred"],"fullname":"dns.message._WireReader.keyring","name":"keyring","type":{".class":"AnyType","missing_import_name":null,"source_any":null,"type_of_any":1}}},"message":{".class":"SymbolTableNode","implicit":true,"kind":"Mdef","node":{".class":"Var","flags":["is_inferred"],"fullname":"dns.message._WireReader.message","name":"message","type":{".class":"AnyType","missing_import_name":null,"source_any":null,"type_of_any":1}}},"multi":{".class":"SymbolTableNode","implicit":true,"kind":"Mdef","node":{".class":"Var","flags":["is_inferred"],"fullname":"dns.message._WireReader.multi","name":"multi","type":{".class":"AnyType","missing_import_name":null,"source_any":null,"type_of_any":1}}},"one_rr_per_rrset":{".class":"SymbolTableNode","implicit":true,"kind":"Mdef","node":{".class":"Var","flags":["is_inferred"],"fullname":"dns.message._WireReader.one_rr_per_rrset","name":"one_rr_per_rrset","type":{".class":"AnyType","missing_import_name":null,"source_any":null,"type_of_any":1}}},"parser":{".class":"SymbolTableNode","implicit":true,"kind":"Mdef","node":{".class":"Var","flags":["is_inferred"],"fullname":"dns.message._WireReader.parser","name":"parser","type":{".class":"AnyType","missing_import_name":null,"source_any":null,"type_of_any":1}}},"question_only":{".class":"SymbolTableNode","implicit":true,"kind":"Mdef","node":{".class":"Var","flags":["is_inferred"],"fullname":"dns.message._WireReader.question_only","name":"question_only","type":{".class":"AnyType","missing_import_name":null,"source_any":null,"type_of_any":1}}},"read":{".class":"SymbolTableNode","kind":"Mdef","node":{".class":"FuncDef","abstract_status":0,"arg_kinds":[0],"arg_names":["self"],"dataclass_transform_spec":null,"flags":[],"fullname":"dns.message._WireReader.read","name":"read","type":null}}},"self_type":{".class":"TypeVarType","default":{".class":"AnyType","missing_import_name":null,"source_any":null,"type_of_any":4},"fullname":"dns.message._WireReader.Self","id":0,"name":"Self","namespace":"","upper_bound":"dns.message._WireReader","values":[],"variance":0},"slots":null,"tuple_type":null,"type_vars":[],"typeddict_type":null}},"__annotations__":{".class":"SymbolTableNode","kind":"Gdef","node":{".class":"Var","flags":["is_ready"],"fullname":"dns.message.__annotations__","name":"__annotations__","type":{".class":"Instance","args":["builtins.str",{".class":"AnyType","missing_import_name":null,"source_any":null,"type_of_any":6}],"type_ref":"builtins.dict"}}},"__doc__":{".class":"SymbolTableNode","kind":"Gdef","node":{".class":"Var","flags":["is_ready"],"fullname":"dns.message.__doc__","name":"__doc__","type":"builtins.str"}},"__file__":{".class":"SymbolTableNode","kind":"Gdef","node":{".class":"Var","flags":["is_ready"],"fullname":"dns.message.__file__","name":"__file__","type":"builtins.str"}},"__name__":{".class":"SymbolTableNode","kind":"Gdef","node":{".class":"Var","flags":["is_ready"],"fullname":"dns.message.__name__","name":"__name__","type":"builtins.str"}},"__package__":{".class":"SymbolTableNode","kind":"Gdef","node":{".class":"Var","flags":["is_ready"],"fullname":"dns.message.__package__","name":"__package__","type":"builtins.str"}},"_maybe_import_update":{".class":"SymbolTableNode","kind":"Gdef","node":{".class":"FuncDef","abstract_status":0,"arg_kinds":[],"arg_names":[],"dataclass_transform_spec":null,"flags":[],"fullname":"dns.message._maybe_import_update","name":"_maybe_import_update","type":null}},"_message_factory_from_opcode":{".class":"SymbolTableNode","kind":"Gdef","node":{".class":"FuncDef","abstract_status":0,"arg_kinds":[0],"arg_names":["opcode"],"dataclass_transform_spec":null,"flags":[],"fullname":"dns.message._message_factory_from_opcode","name":"_message_factory_from_opcode","type":null}},"contextlib":{".class":"SymbolTableNode","cross_ref":"contextlib","kind":"Gdef"},"dns":{".class":"SymbolTableNode","cross_ref":"dns","kind":"Gdef"},"from_file":{".class":"SymbolTableNode","kind":"Gdef","node":{".class":"FuncDef","abstract_status":0,"arg_kinds":[0,1,1],"arg_names":["f","idna_codec","one_rr_per_rrset"],"dataclass_transform_spec":null,"flags":[],"fullname":"dns.message.from_file","name":"from_file","type":{".class":"CallableType","arg_kinds":[0,1,1],"arg_names":["f","idna_codec","one_rr_per_rrset"],"arg_types":[{".class":"AnyType","missing_import_name":null,"source_any":null,"type_of_any":2},{".class":"UnionType","items":["dns.name.IDNACodec",{".class":"NoneType"}]},"builtins.bool"],"bound_args":[],"def_extras":{"first_arg":null},"fallback":"builtins.function","from_concatenate":false,"implicit":false,"imprecise_arg_kinds":false,"is_ellipsis_args":false,"name":"from_file","ret_type":"dns.message.Message","type_guard":null,"unpack_kwargs":false,"variables":[]}}},"from_text":{".class":"SymbolTableNode","kind":"Gdef","node":{".class":"FuncDef","abstract_status":0,"arg_kinds":[0,1,1,1,1,1],"arg_names":["text","idna_codec","one_rr_per_rrset","origin","relativize","relativize_to"],"dataclass_transform_spec":null,"flags":[],"fullname":"dns.message.from_text","name":"from_text","type":{".class":"CallableType","arg_kinds":[0,1,1,1,1,1],"arg_names":["text","idna_codec","one_rr_per_rrset","origin","relativize","relativize_to"],"arg_types":["builtins.str",{".class":"UnionType","items":["dns.name.IDNACodec",{".class":"NoneType"}]},"builtins.bool",{".class":"UnionType","items":["dns.name.Name",{".class":"NoneType"}]},"builtins.bool",{".class":"UnionType","items":["dns.name.Name",{".class":"NoneType"}]}],"bound_args":[],"def_extras":{"first_arg":null},"fallback":"builtins.function","from_concatenate":false,"implicit":false,"imprecise_arg_kinds":false,"is_ellipsis_args":false,"name":"from_text","ret_type":"dns.message.Message","type_guard":null,"unpack_kwargs":false,"variables":[]}}},"from_wire":{".class":"SymbolTableNode","kind":"Gdef","node":{".class":"FuncDef","abstract_status":0,"arg_kinds":[0,1,1,1,1,1,1,1,1,1,1,1],"arg_names":["wire","keyring","request_mac","xfr","origin","tsig_ctx","multi","question_only","one_rr_per_rrset","ignore_trailing","raise_on_truncation","continue_on_error"],"dataclass_transform_spec":null,"flags":[],"fullname":"dns.message.from_wire","name":"from_wire","type":{".class":"CallableType","arg_kinds":[0,1,1,1,1,1,1,1,1,1,1,1],"arg_names":["wire","keyring","request_mac","xfr","origin","tsig_ctx","multi","question_only","one_rr_per_rrset","ignore_trailing","raise_on_truncation","continue_on_error"],"arg_types":["builtins.bytes",{".class":"UnionType","items":[{".class":"AnyType","missing_import_name":null,"source_any":null,"type_of_any":2},{".class":"NoneType"}]},{".class":"UnionType","items":["builtins.bytes",{".class":"NoneType"}]},"builtins.bool",{".class":"UnionType","items":["dns.name.Name",{".class":"NoneType"}]},{".class":"UnionType","items":["dns.tsig.HMACTSig","dns.tsig.GSSTSig",{".class":"NoneType"}]},"builtins.bool","builtins.bool","builtins.bool","builtins.bool","builtins.bool","builtins.bool"],"bound_args":[],"def_extras":{"first_arg":null},"fallback":"builtins.function","from_concatenate":false,"implicit":false,"imprecise_arg_kinds":false,"is_ellipsis_args":false,"name":"from_wire","ret_type":"dns.message.Message","type_guard":null,"unpack_kwargs":false,"variables":[]}}},"io":{".class":"SymbolTableNode","cross_ref":"io","kind":"Gdef"},"make_query":{".class":"SymbolTableNode","kind":"Gdef","node":{".class":"FuncDef","abstract_status":0,"arg_kinds":[0,0,1,1,1,1,1,1,1,1,1,1,1],"arg_names":["qname","rdtype","rdclass","use_edns","want_dnssec","ednsflags","payload","request_payload","options","idna_codec","id","flags","pad"],"dataclass_transform_spec":null,"flags":[],"fullname":"dns.message.make_query","name":"make_query","type":{".class":"CallableType","arg_kinds":[0,0,1,1,1,1,1,1,1,1,1,1,1],"arg_names":["qname","rdtype","rdclass","use_edns","want_dnssec","ednsflags","payload","request_payload","options","idna_codec","id","flags","pad"],"arg_types":[{".class":"UnionType","items":["dns.name.Name","builtins.str"]},{".class":"UnionType","items":["dns.rdatatype.RdataType","builtins.str"]},{".class":"UnionType","items":["dns.rdataclass.RdataClass","builtins.str"]},{".class":"UnionType","items":["builtins.int","builtins.bool",{".class":"NoneType"}]},"builtins.bool",{".class":"UnionType","items":["builtins.int",{".class":"NoneType"}]},{".class":"UnionType","items":["builtins.int",{".class":"NoneType"}]},{".class":"UnionType","items":["builtins.int",{".class":"NoneType"}]},{".class":"UnionType","items":[{".class":"Instance","args":["dns.edns.Option"],"type_ref":"builtins.list"},{".class":"NoneType"}]},{".class":"UnionType","items":["dns.name.IDNACodec",{".class":"NoneType"}]},{".class":"UnionType","items":["builtins.int",{".class":"NoneType"}]},"builtins.int","builtins.int"],"bound_args":[],"def_extras":{"first_arg":null},"fallback":"builtins.function","from_concatenate":false,"implicit":false,"imprecise_arg_kinds":false,"is_ellipsis_args":false,"name":"make_query","ret_type":"dns.message.QueryMessage","type_guard":null,"unpack_kwargs":false,"variables":[]}}},"make_response":{".class":"SymbolTableNode","kind":"Gdef","node":{".class":"FuncDef","abstract_status":0,"arg_kinds":[0,1,1,1,1,1],"arg_names":["query","recursion_available","our_payload","fudge","tsig_error","pad"],"dataclass_transform_spec":null,"flags":[],"fullname":"dns.message.make_response","name":"make_response","type":{".class":"CallableType","arg_kinds":[0,1,1,1,1,1],"arg_names":["query","recursion_available","our_payload","fudge","tsig_error","pad"],"arg_types":["dns.message.Message","builtins.bool","builtins.int","builtins.int","builtins.int",{".class":"UnionType","items":["builtins.int",{".class":"NoneType"}]}],"bound_args":[],"def_extras":{"first_arg":null},"fallback":"builtins.function","from_concatenate":false,"implicit":false,"imprecise_arg_kinds":false,"is_ellipsis_args":false,"name":"make_response","ret_type":"dns.message.Message","type_guard":null,"unpack_kwargs":false,"variables":[]}}},"time":{".class":"SymbolTableNode","cross_ref":"time","kind":"Gdef"}},"path":"c:\\Users\\Mateen\\AppData\\Local\\pypoetry\\Cache\\virtualenvs\\api-ag0NGuHR-py3.12\\Lib\\site-packages\\dns\\message.py"}